Workbook

Sheet Scenario background
A1: Energy production per scenario | B1: Unit | C1: Sector | D1: EP2050+ | E1: MIX | F1: RE MIX | G1: H2 | L1: Technology SUM | M1: EP2050+ | N1: MIX | O1: RE MIX | P1: H2
A2: Biomass Boiler | B2: [TWh] | C2: Buildings Heat | D2: 32.72 | E2: 0 | F2: 18.24 | G2: 34.85 | L2: Biomass Boiler | M2: =D2 -> 32.72 | N2: =E2 -> 0 | O2: =F2 -> 18.24 | P2: =G2 -> 34.85
A3: Heat Pump | B3: [TWh] | C3: Buildings Heat | D3: 19.988 | E3: 55.11 | F3: 36.87 | G3: 1.63 | L3: Heat Pump | M3: =D3+D16 -> 24.279 | N3: =E3+E16 -> 63.82 | O3: =F3+F16 -> 41.27 | P3: =G3+G16 -> 9.56
A4: Methane Boiler | B4: [TWh] | C4: Buildings Heat | D4: 2.4 | E4: 0 | F4: 0 | G4: 18.63 | L4: Methane Boiler | M4: =D4+D15 -> 8.102 | N4: =E4+E15 -> 5.702 | O4: =F4+F15 -> 5.702 | P4: =G4+G15 -> 24.33
A5: CCGT (Ren. Methane) | B5: [TWh] | C5: Electricity | D5: 0 | E5: 0 | F5: 4.28 | G5: 0 | L5: CCGT (Ren. Methane) | M5: =D5 -> 0 | N5: =E5 -> 0 | O5: =F5 -> 4.28 | P5: =G5 -> 0
A6: CHP (waste) | B6: [TWh] | C6: Electricity | D6: =2688.99874401158/1000 -> 2.6889987 | E6: =2689.00014668487/1000 -> 2.6890001 | F6: =2689.00043712191/1000 -> 2.6890004 | G6: =[1]Overview!J22/1000 -> 2.688993 | L6: CHP (waste) | M6: =D6+D17 -> 8.7389987 | N6: =E6+E17 -> 8.7390001 | O6: =F6+F17 -> 8.7390004 | P6: =G6+G17 -> 8.738993
A7: CHP (Ren. Methane) | B7: [TWh] | C7: Electricity | D7: =2451.80310776911/1000 -> 2.4518031 | E7: =0.002037654/1000 -> 2.037654e-06 | F7: =0.01612777/1000 -> 1.612777e-05 | G7: =[1]Overview!J21/1000 -> 2.45182 | L7: CHP (Ren. Methane) | M7: =D7 -> 2.4518031 | N7: =E7 -> 2.037654e-06 | O7: =F7 -> 1.612777e-05 | P7: =G7 -> 2.45182
A8: Hydro (reservoir) | B8: [TWh] | C8: Electricity | D8: 16.05 | E8: 17.37 | F8: 16.05 | G8: 18.26 | L8: Hydro (reservoir) | M8: =D8 -> 16.05 | N8: =E8 -> 17.37 | O8: =F8 -> 16.05 | P8: =G8 -> 18.26
A9: Hydro (run of) | B9: [TWh] | C9: Electricity | D9: 15.49 | E9: 15.49 | F9: 15.49 | G9: 15.49 | L9: Hydro (run of) | M9: =D9 -> 15.49 | N9: =E9 -> 15.49 | O9: =F9 -> 15.49 | P9: =G9 -> 15.49
A10: PV (Roof) | B10: [TWh] | C10: Electricity | D10: 33.61 | E10: 30.22 | F10: 30.25 | G10: 33.61 | L10: PV (Roof) | M10: =D10 -> 33.61 | N10: =E10 -> 30.22 | O10: =F10 -> 30.25 | P10: =G10 -> 33.61
A11: Pumped Hydro | B11: [TWh] | C11: Electricity | D11: 5.67 | E11: 7.92 | F11: 6.72 | G11: 6.09 | L11: Pumped Hydro | M11: =D11 -> 5.67 | N11: =E11 -> 7.92 | O11: =F11 -> 6.72 | P11: =G11 -> 6.09
A12: Wind | B12: [TWh] | C12: Electricity | D12: 4.04 | E12: 7.32 | F12: 8.04 | G12: 4.12 | L12: Wind | M12: =D12 -> 4.04 | N12: =E12 -> 7.32 | O12: =F12 -> 8.04 | P12: =G12 -> 4.12
A13: CCGT (Nat Gas) | B13: [TWh] | C13: Electricity | D13: 0 | E13: 12.65 | F13: 0 | G13: 0 | L13: CCGT (Nat Gas) | M13: =D13 -> 0 | N13: =E13 -> 12.65 | O13: =F13 -> 0 | P13: =G13 -> 0
A14: Alpine PV | B14: [TWh] | C14: Electricity | D14: 0 | E14: 0 | F14: 7.06 | G14: 0 | L14: Alpine PV | M14: =D14 -> 0 | N14: =E14 -> 0 | O14: =F14 -> 7.06 | P14: =G14 -> 0
A15: Methane Boiler | B15: [TWh] | C15: Industrial Heat (HT Heat) | D15: 5.702 | E15: 5.702 | F15: 5.702 | G15: 5.7 | L15: Heavy EV | M15: =D18 -> 3.2 | N15: =E18 -> 3.2 | O15: =F18 -> 3.2 | P15: =G18 -> 0
A16: Heat Pump | B16: [TWh] | C16: Industrial Heat (LT Heat) | D16: 4.291 | E16: 8.71 | F16: 4.4 | G16: 7.93 | L16: Heavy FCEV | M16: =D19 -> 0 | N16: =E19 -> 0 | O16: =F19 -> 0 | P16: =G19 -> 3.2
A17: CHP (waste) | B17: [TWh] | C17: Industrial Heat (MT Heat) | D17: 6.05 | E17: 6.05 | F17: 6.05 | G17: 6.05 | L17: Light EV | M17: =D20 -> 74.79 | N17: =E20 -> 74.79 | O17: =F20 -> 74.79 | P17: =G20 -> 69.22
A18: Heavy EV | B18: [Bil. km] | C18: Transport (Heavy) | D18: 3.2 | E18: 3.2 | F18: 3.2 | G18: 0 | L18: Light FCEV | M18: =D21 -> 0 | N18: =E21 -> 0 | O18: =F21 -> 0 | P18: =G21 -> 5.57
A19: Heavy FCEV | B19: [Bil. km] | C19: Transport (Heavy) | D19: 0 | E19: 0 | F19: 0 | G19: 3.2
A20: Light EV | B20: [Bil. km] | C20: Transport (Light) | D20: 74.79 | E20: 74.79 | F20: 74.79 | G20: 69.22 | L20: Technology SUM | M20: Biomass Boiler | N20: Heat Pump | O20: Methane Boiler | P20: CCGT (Ren. Methane) | Q20: CHP (waste) | R20: CHP (methane) | S20: Hydro (reservoir) | T20: Hydro (run of) | U20: PV (Roof) | V20: Pumped Hydro | W20: Wind | X20: CCGT (Nat Gas) | Y20: Alpine PV | Z20: Heavy EV | AA20: Heavy FCEV | AB20: Light EV | AC20: Light FCEV
A21: Light FCEV | B21: [Bil. km] | C21: Transport (Light) | D21: 0 | E21: 0 | F21: 0 | G21: 5.57 | L21: EP2050+ | M21: 32.72 | N21: 24.279 | O21: 8.102 | P21: 0 | Q21: 8.7389987 | R21: 2.4518031 | S21: 16.05 | T21: 15.49 | U21: 33.61 | V21: 5.67 | W21: 4.04 | X21: 0 | Y21: 0 | Z21: 3.2 | AA21: 0 | AB21: 74.79 | AC21: 0
L22: MIX | M22: 0 | N22: 63.82 | O22: 5.702 | P22: 0 | Q22: 8.7390001 | R22: 2.037654e-06 | S22: 17.37 | T22: 15.49 | U22: 30.22 | V22: 7.92 | W22: 7.32 | X22: 12.65 | Y22: 0 | Z22: 3.2 | AA22: 0 | AB22: 74.79 | AC22: 0
L23: RE MIX | M23: 18.24 | N23: 41.27 | O23: 5.702 | P23: 4.28 | Q23: 8.7390004 | R23: 1.612777e-05 | S23: 16.05 | T23: 15.49 | U23: 30.25 | V23: 6.72 | W23: 8.04 | X23: 0 | Y23: 7.06 | Z23: 3.2 | AA23: 0 | AB23: 74.79 | AC23: 0
L24: H2 | M24: 34.85 | N24: 9.56 | O24: 24.33 | P24: 0 | Q24: 8.738993 | R24: 2.45182 | S24: 18.26 | T24: 15.49 | U24: 33.61 | V24: 6.09 | W24: 4.12 | X24: 0 | Y24: 0 | Z24: 0 | AA24: 3.2 | AB24: 69.22 | AC24: 5.57

Sheet Relative tech support level
B1: Biomass Boiler | C1: Heat Pump | D1: Methane Boiler | E1: CCGT (Ren. Methane) | F1: CHP (waste) | G1: CHP (Ren. Methane) | H1: Hydro (reservoir) | I1: Hydro (run of) | J1: PV (Roof) | K1: Pumped Hydro | L1: Wind | M1: CCGT (Nat Gas) | N1: Alpine PV | O1: Heavy EV | P1: Heavy FCEV | Q1: Light EV | R1: Light FCEV
A2: EP2050+ | B2: NA | C2: NA | D2: NA | E2: NA | F2: NA | G2: NA | H2: NA | I2: NA | J2: NA | K2: NA | L2: NA | M2: NA | N2: NA | O2: NA | P2: NA | Q2: NA | R2: NA
A3: MIX | B3: =('Scenario background'!M22-'Scenario background'!M$21)/SUM('Scenario background'!$M$21:$Y$21) -> -0.21647112 | C3: =('Scenario background'!N22-'Scenario background'!N$21)/SUM('Scenario background'!$M$21:$Y$21) -> 0.26159794 | D3: =('Scenario background'!O22-'Scenario background'!O$21)/SUM('Scenario background'!$M$21:$Y$21) -> -0.015878077 | E3: =('Scenario background'!P22-'Scenario background'!P$21)/SUM('Scenario background'!$M$21:$Y$21) -> 0 | F3: =('Scenario background'!Q22-'Scenario background'!Q$21)/SUM('Scenario background'!$M$21:$Y$21) -> 9.2798979e-09 | G3: =('Scenario background'!R22-'Scenario background'!R$21)/SUM('Scenario background'!$M$21:$Y$21) -> -0.016220786 | H3: =('Scenario background'!S22-'Scenario background'!S$21)/SUM('Scenario background'!$M$21:$Y$21) -> 0.0087329425 | I3: =('Scenario background'!T22-'Scenario background'!T$21)/SUM('Scenario background'!$M$21:$Y$21) -> 0 | ... N3: =('Scenario background'!Y22-'Scenario background'!Y$21)/SUM('Scenario background'!$M$21:$Y$21) -> 0 | O3: =('Scenario background'!Z22-'Scenario background'!Z$21)/SUM('Scenario background'!$Z$21:$AC$21) -> 0 | P3: =('Scenario background'!AA22-'Scenario background'!AA$21)/SUM('Scenario background'!$Z$21:$AC$21) -> 0 | Q3: =('Scenario background'!AB22-'Scenario background'!AB$21)/SUM('Scenario background'!$Z$21:$AC$21) -> 0 | R3: =('Scenario background'!AC22-'Scenario background'!AC$21)/SUM('Scenario background'!$Z$21:$AC$21) -> 0
A4: REMIX | B4: =('Scenario background'!M23-'Scenario background'!M$21)/SUM('Scenario background'!$M$21:$Y$21) -> -0.095797733 | C4: =('Scenario background'!N23-'Scenario background'!N$21)/SUM('Scenario background'!$M$21:$Y$21) -> 0.11241017 | D4: =('Scenario background'!O23-'Scenario background'!O$21)/SUM('Scenario background'!$M$21:$Y$21) -> -0.015878077 | E4: =('Scenario background'!P23-'Scenario background'!P$21)/SUM('Scenario background'!$M$21:$Y$21) -> 0.028315905 | F4: =('Scenario background'!Q23-'Scenario background'!Q$21)/SUM('Scenario background'!$M$21:$Y$21) -> 1.120139e-08 | G4: =('Scenario background'!R23-'Scenario background'!R$21)/SUM('Scenario background'!$M$21:$Y$21) -> -0.016220693 | H4: =('Scenario background'!S23-'Scenario background'!S$21)/SUM('Scenario background'!$M$21:$Y$21) -> 0 | I4: =('Scenario background'!T23-'Scenario background'!T$21)/SUM('Scenario background'!$M$21:$Y$21) -> 0 | ... N4: =('Scenario background'!Y23-'Scenario background'!Y$21)/SUM('Scenario background'!$M$21:$Y$21) -> 0.046708011 | O4: =('Scenario background'!Z23-'Scenario background'!Z$21)/SUM('Scenario background'!$Z$21:$AC$21) -> 0 | P4: =('Scenario background'!AA23-'Scenario background'!AA$21)/SUM('Scenario background'!$Z$21:$AC$21) -> 0 | Q4: =('Scenario background'!AB23-'Scenario background'!AB$21)/SUM('Scenario background'!$Z$21:$AC$21) -> 0 | R4: =('Scenario background'!AC23-'Scenario background'!AC$21)/SUM('Scenario background'!$Z$21:$AC$21) -> 0
A5: H2 | B5: =('Scenario background'!M24-'Scenario background'!M$21)/SUM('Scenario background'!$M$21:$Y$21) -> 0.014091794 | C5: =('Scenario background'!N24-'Scenario background'!N$21)/SUM('Scenario background'!$M$21:$Y$21) -> -0.097378925 | D5: =('Scenario background'!O24-'Scenario background'!O$21)/SUM('Scenario background'!$M$21:$Y$21) -> 0.10736227 | E5: =('Scenario background'!P24-'Scenario background'!P$21)/SUM('Scenario background'!$M$21:$Y$21) -> 0 | F5: =('Scenario background'!Q24-'Scenario background'!Q$21)/SUM('Scenario background'!$M$21:$Y$21) -> -3.7788348e-08 | G5: =('Scenario background'!R24-'Scenario background'!R$21)/SUM('Scenario background'!$M$21:$Y$21) -> 1.1181451e-07 | H5: =('Scenario background'!S24-'Scenario background'!S$21)/SUM('Scenario background'!$M$21:$Y$21) -> 0.014621063 | I5: =('Scenario background'!T24-'Scenario background'!T$21)/SUM('Scenario background'!$M$21:$Y$21) -> 0 | ... N5: =('Scenario background'!Y24-'Scenario background'!Y$21)/SUM('Scenario background'!$M$21:$Y$21) -> 0 | O5: =('Scenario background'!Z24-'Scenario background'!Z$21)/SUM('Scenario background'!$Z$21:$AC$21) -> -0.041030901 | P5: =('Scenario background'!AA24-'Scenario background'!AA$21)/SUM('Scenario background'!$Z$21:$AC$21) -> 0.041030901 | Q5: =('Scenario background'!AB24-'Scenario background'!AB$21)/SUM('Scenario background'!$Z$21:$AC$21) -> -0.071419413 | R5: =('Scenario background'!AC24-'Scenario background'!AC$21)/SUM('Scenario background'!$Z$21:$AC$21) -> 0.071419413
C7: Unit: TWh | E7: Power and heating
C8: Unit: Bil. Km | E8: Transport

Sheet Policy Evaluation List
D1: ID | E1: Policy | F1: Status | G1: Policy Instrument | H1: Intensity | M1: Technology | AD1: comments
H2: Much Lower | I2: Lower | J2: Current | K2: Higher | L2: Much Higher | M2: Biomass Boiler | N2: Heat Pump | O2: Methane Boiler | P2: CCGT (Ren. Methane) | Q2: CHP (waste) | R2: CHP (Ren. Methane) | S2: Hydro (reservoir) | T2: Hydro (run of) | U2: PV (Roof) | V2: Pumped Hydro | W2: Wind | X2: CCGT (Nat Gas) with DACCS | Y2: Alpine PV | Z2: Heavy EV | AA2: Heavy FCEV | AB2: Light EV | AC2: Light FCEV
A3: I | B3: 01 | C3: 1-5 | D3: =A3 & "_" & B3 & "_" & C3 -> I_01_1-5 | E3: Carbon tax - thermal fuels & natural gas | F3: In force | G3: Tax | H3: 60 CHF/tCO2eq | I3: 90 CHF/tCO2eq | J3: 120 CHF/tCO2eq | K3: 180 CHF/tCO2eq | L3: 240 CHF/tCO2eq | M3: 0.2 | N3: 0.2 | O3: 0.2 | Q3: 0.2 | R3: 0.2
A4: N | B4: 02 | C4: 4-5 | D4: =A4 & "_" & B4 & "_" & C4 -> N_02_4-5 | E4: Carbon tax - motor fuels | F4: Non-existent | G4: Tax | H4: / | I4: / | J4: / | K4: 60 CHF/tCO2eq | L4: 80 CHF/tCO2eq | Z4: 0.25 | AA4: 0.25 | AB4: 0.25 | AC4: 0.25
A5: I | B5: 03 | C5: 1-3 | D5: =A5 & "_" & B5 & "_" & C5 -> I_03_1-3 | E5: Reimbursement of the carbon tax for CHP (nat gas) | F5: In force | G5: Fiscal exemption | H5: Obtain 20% reimbursement of the CO₂ levy for the fraction used for electricity generation with mandatory energy‑efficiency investment (40%) | I5: Obtain 60% reimbursement of the CO₂ levy for the fraction used for electricity generation with mandatory energy‑efficiency investment (40%) | J5: Obtain a reimbursement of the CO₂ levy for the fraction used for electricity generation with mandatory energy‑efficiency investment (40%) | K5: / | L5: / | R5: 1
A6: I | B6: 04 | C6: 3-5 | D6: =A6 & "_" & B6 & "_" & C6 -> I_04_3-5 | E6: Mineral oil tax - thermal fuels & natural gas | F6: In force | G6: Tax | H6: / | I6: / | J6: 0.3 centimes/L | K6: 15 centimes/L | L6: 30 centimes/L | M6: 0.2 | N6: 0.2 | O6: 0.2 | Q6: 0.2 | R6: 0.2
A7: I | B7: 05 | C7: 1-5 | D7: =A7 & "_" & B7 & "_" & C7 -> I_05_1-5 | E7: Mineral oil tax - motor fuels | F7: In force | G7: Tax | H7: 40 centimes/L | I7: 60 centimes/L | J7: 76.82-79.57 centimes/L | K7: 100 centimes/L | L7: 120 centimes/L | Z7: 0.25 | AA7: 0.25 | AB7: 0.25 | AC7: 0.25
A8: I | B8: 06 | C8: 1-5 | D8: =A8 & "_" & B8 & "_" & C8 -> I_06_1-5 | E8: ETS - Installations >= 20 MW | F8: In force | G8: ETS | H8: The cap will reach 0 in 2050 | I8: The cap will reach 0 in 2045 | J8: The cap will reach 0 in 2040 | K8: The cap will reach 0 in 2035 | L8: The cap will reach 0 in 2030 | P8: 0.1 | Q8: 0.1 | R8: 0.1 | S8: 0.1 | T8: 0.1 | U8: 0.1 | V8: 0.1 | W8: 0.1 | X8: 0.1 | Y8: 0.1
A9: N | B9: 07 | C9: 4-5 | D9: =A9 & "_" & B9 & "_" & C9 -> N_07_4-5 | E9: Carbon removal for fossil electricity generation plants | F9: Non-existent | G9: Obligation | H9: / | I9: / | J9: / | K9: 0.5 | L9: 1 | X9: 1
A10: N | B10: 08 | C10: 4-5 | D10: =A10 & "_" & B10 & "_" & C10 -> N_08_4-5 | E10: subsidy on DACCS | F10: Non-existent | G10: Subsidy | H10: / | I10: / | J10: / | K10: up to 30% CAPEX | L10: up to 60% CAPEX | X10: 1
A11: I | B11: 09 | C11: 1-5 | D11: =A11 & "_" & B11 & "_" & C11 -> I_09_1-5 | E11: Subisidy for district heat connection | F11: In force | G11: Subsidy | H11: 30% lower | I11: 10% lower | J11: 106-1320 CHF/kW | K11: 10% higher | L11: 30% higher | M11: 0.25 | N11: 0.25 | Q11: 0.25 | R11: 0.25
A12: I | B12: 10 | C12: 1-5 | D12: =A12 & "_" & B12 & "_" & C12 -> I_10_1-5 | E12: subsidy on the heat distribution system | F12: In force | G12: Subsidy | H12: 30% lower | I12: 10% lower | J12: 60-300 CHF/m2 | K12: 10% higher | L12: 30% higher | M12: 0.2 | N12: 0.2 | O12: 0.2 | Q12: 0.2 | R12: 0.2
A13: I | B13: 11 | C13: 1-5 | D13: =A13 & "_" & B13 & "_" & C13 -> I_11_1-5 | E13: subsidy on heat pumps | F13: In force | G13: Subsidy | H13: 30% lower | I13: 10% lower | J13: 64-2360 CHF/ kW | K13: 10% higher | L13: 30% higher | N13: 1
A14: I | B14: 12 | C14: 1-5 | D14: =A14 & "_" & B14 & "_" & C14 -> I_12_1-5 | E14: subsidy on wood heaters | F14: In force | G14: Subsidy | H14: 30% lower | I14: 10% lower | J14: 59-720 CHF/kW | K14: 10% higher | L14: 30% higher | M14: 1
A15: I | B15: 13 | C15: 3-5 | D15: =A15 & "_" & B15 & "_" & C15 -> I_13_3-5 | E15: Ban on gas boilers | F15: In force | G15: Ban | H15: / | I15: / | J15: When a boiler reaches the end of its life, cantonal energy laws (based on the MuKEn guidelines) often prohibit replacing it with another fossil fuel system. | K15: Ban on all new installations. | L15: Ban on all gas boilers with the use of natural gas. | M15: 0.2 | N15: 0.2 | O15: 0.2 | Q15: 0.2 | R15: 0.2
A16: I | B16: 14 | C16: 3-5 | D16: =A16 & "_" & B16 & "_" & C16 -> I_14_3-5 | E16: Ban on nuclear power plants | F16: In force | G16: Ban | H16: / | I16: / | J16: No permits for the construction of new nuclear power plants or any basic changes to existing nuclear power plants will be delivered. The existing nuclear power plants may stay in operation for as long as they remain safe. | K16: 60 years of operation | L16: 50 years of operation | P16: 0.1 | Q16: 0.1 | R16: 0.1 | S16: 0.1 | T16: 0.1 | U16: 0.1 | V16: 0.1 | W16: 0.1 | X16: 0.1 | Y16: 0.1
A17: I | B17: 15 | C17: 1-5 | D17: =A17 & "_" & B17 & "_" & C17 -> I_15_1-5 | E17: subsidy on CHP | F17: In force | G17: Subsidy | H17: 30% lower | I17: 10% lower | J17: 70-1060 CHF/kW | K17: 10% higher | L17: 30% higher | Q17: 0.5 | R17: 0.5
A18: I | B18: 16 | C18: 1-5 | D18: =A18 & "_" & B18 & "_" & C18 -> I_16_1-5 | E18: One-off remuneration (EIV) for PV | F18: In force | G18: Subsidy | H18: up to 10% CAPEX | I18: up to 20% CAPEX | J18: up to 30% CAPEX | K18: up to 40% CAPEX | L18: up to 50% CAPEX | U18: 0.5 | Y18: 0.5
A19: I | B19: 17 | C19: 1-5 | D19: =A19 & "_" & B19 & "_" & C19 -> I_17_1-5 | E19: High one-off remuneration (EIV) for PV with auctions | F19: In force | G19: Subsidy | H19: up to 30% CAPEX | I19: up to 45% CAPEX | J19: up to 60% CAPEX | K19: up to 65% CAPEX | L19: up to 70% CAPEX | U19: 0.5 | Y19: 0.5
A20: I | B20: 18 | C20: 1-5 | D20: =A20 & "_" & B20 & "_" & C20 -> I_18_1-5 | E20: Sliding market premium (GMP) for PV with auctions | F20: In force | G20: Subsidy | H20: 6 Rp./kWh for 20 years | I20: 8 Rp./kWh for 20 years | J20: 10 Rp./kWh for 20 years | K20: 11 Rp./kWh for 20 years | L20: 12 Rp./kWh for 20 years | U20: 0.5 | Y20: 0.5
A21: I | B21: 19 | C21: 1-5 | D21: =A21 & "_" & B21 & "_" & C21 -> I_19_1-5 | E21: Purchase remuneration for PV | F21: In force | G21: Market design | H21: daily average market price | I21: monthly average market price | J21: producers and grid operators' agreement on the sale price - reference price: quarterly average market price | K21: half-yearly average market price | L21: yearly average market price | U21: 0.5 | Y21: 0.5
A22: I | B22: 20 | C22: 1-5 | D22: =A22 & "_" & B22 & "_" & C22 -> I_20_1-5 | E22: Minimum tariffs for photovoltaic systems <= 150 kW | F22: In force | G22: Market design | H22: 1-4 Rp./kWh | I22: 1-5 Rp./kWh | J22: 1.2-6.2 Rp./kWh | K22: 3-8 Rp./kWh | L22: 5-10 Rp./kWh | U22: 0.5 | Y22: 0.5
A23: N | B23: 21 | C23: 4-5 | D23: =A23 & "_" & B23 & "_" & C23 -> N_21_4-5 | E23: Project planning grants for Alpine PV | F23: Non-existent | G23: Subsidy | H23: / | I23: / | J23: / | K23: up to 30% CAPEX | L23: up to 60% CAPEX | Y23: 1
A24: I | B24: 22 | C24: 1-5 | D24: =A24 & "_" & B24 & "_" & C24 -> I_22_1-5 | E24: Sliding market premium (GMP) for Biomass electricity generation | F24: In force | G24: Subsidy | H24: 30% lower | I24: 10% lower | J24: 16.5-27 Rp./kWh for 20 years | K24: 10% higher | L24: 30% higher | P24: 0.5 | R24: 0.5
A25: I | B25: 23 | C25: 1-5 | D25: =A25 & "_" & B25 & "_" & C25 -> I_23_1-5 | E25: Operating cost contribution (BKB) for Biomass electricity generation | F25: In force | G25: Subsidy | H25: 30% lower | I25: 10% lower | J25: 9-12 Rp./kWh | K25: 10% higher | L25: 30% higher | P25: 0.5 | R25: 0.5
A26: I | B26: 24 | C26: 1-5 | D26: =A26 & "_" & B26 & "_" & C26 -> I_24_1-5 | E26: Investment contribution (IB) for Biomass electricity generation | F26: In force | G26: Subsidy | H26: up to 30% CAPEX | I26: up to 45% CAPEX | J26: up to 60% CAPEX | K26: up to 65% CAPEX | L26: up to 70% CAPEX | P26: 0.33 | Q26: 0.33 | R26: 0.33
A27: I | B27: 25 | C27: 1-5 | D27: =A27 & "_" & B27 & "_" & C27 -> I_25_1-5 | E27: Sliding market premium (GMP) for hydro power | F27: In force | G27: Subsidy | H27: 30% lower | I27: 10% lower | J27: ~ 1.0 Rp/kWh | K27: 10% higher | L27: 30% higher | S27: 0.33 | T27: 0.33 | V27: 0.33 | AD27: https://www.igeb.ch/grosswasserkraft/
A28: I | B28: 26 | C28: 1-5 | D28: =A28 & "_" & B28 & "_" & C28 -> I_26_1-5 | E28: Investment contribution (IB) for hydro power | F28: In force | G28: Subsidy | H28: ~ 10% CAPEX | I28: ~ 20% CAPEX | J28: ~ 30% CAPEX | K28: ~ 40% CAPEX | L28: ~ 50% CAPEX | S28: 0.33 | T28: 0.33 | V28: 0.33 | AD28: https://www.admin.ch/de/nsb?id=86561
A29: I | B29: 27 | C29: 1-5 | D29: =A29 & "_" & B29 & "_" & C29 -> I_27_1-5 | E29: Project planning contributions for new hydroelectric power plants or significant expansions of hydroelectric power plants | F29: In force | G29: Subsidy | H29: up to 20% CAPEX | I29: up to 30% CAPEX | J29: up to 40% CAPEX | K29: up to 50% CAPEX | L29: up to 60% CAPEX | S29: 0.33 | T29: 0.33 | V29: 0.33
A30: I | B30: 28 | C30: 1-5 | D30: =A30 & "_" & B30 & "_" & C30 -> I_28_1-5 | E30: Sliding market premium (GMP) for wind energy | F30: In force | G30: Subsidy | H30: 30% lower | I30: 10% lower | J30: ~ 9-12 Rp./kWh for 20 years | K30: 10% higher | L30: 30% higher | W30: 1
A31: I | B31: 29 | C31: 1-5 | D31: =A31 & "_" & B31 & "_" & C31 -> I_29_1-5 | E31: Investment contribution (IB) for wind energy | F31: In force | G31: Subsidy | H31: ~ 10% CAPEX | I31: ~ 15% CAPEX | J31: ~ 20% CAPEX | K31: ~ 40% CAPEX | L31: ~ 60% CAPEX | W31: 1
A32: I | B32: 30 | C32: 1-5 | D32: =A32 & "_" & B32 & "_" & C32 -> I_30_1-5 | E32: Project planning grants for wind energy | F32: In force | G32: Subsidy | H32: up to 10% CAPEX | I32: up to 20% CAPEX | J32: up to 40% CAPEX | K32: up to 50% CAPEX | L32: up to 60% CAPEX | W32: 1
A33: N | B33: 31 | C33: 4-5 | D33: =A33 & "_" & B33 & "_" & C33 -> N_31_4-5 | E33: Purchase remuneration for wind energy | F33: Non-existent | G33: Market design | H33: / | I33: / | J33: / | K33: producers and grid operators' agreement on the sale price - reference price: monthly average market price | L33: producers and grid operators' agreement on the sale price - reference price: quarterly average market price | W33: 1
A34: N | B34: 32 | C34: 4-5 | D34: =A34 & "_" & B34 & "_" & C34 -> N_32_4-5 | E34: Minimum tariffs for wind energy | F34: Non-existent | G34: Market design | H34: / | I34: / | J34: / | K34: 1.2-6.2 Rp./kWh | L34: 3-8 Rp./kWh | W34: 1
A35: I | B35: 33 | C35: 3-5 | D35: =A35 & "_" & B35 & "_" & C35 -> I_33_3-5 | E35: Reimbursement of network usage charges for Hydrogen and Power-to-X P+D installations | F35: In force | G35: Market design | H35: / | I35: / | J35: 200 MW quota | K35: 600 MW quota | L35: 1000 MW quota | O35: 0.33 | AA35: 0.33 | AC35: 0.33
A36: I | B36: 34 | C36: 1-5 | D36: =A36 & "_" & B36 & "_" & C36 -> I_34_1-5 | E36: Carbon offsetting for motor fuels | F36: In force | G36: Obligation | H36: 50% in 2040 | I36: 50% in 2035 | J36: 50% in 2030 | K36: 0.6 | L36: 1 | Z36: 0.25 | AA36: 0.25 | AB36: 0.25 | AC36: 0.25
A37: I | B37: 35 | C37: 1-5 | D37: =A37 & "_" & B37 & "_" & C37 -> I_35_1-5 | E37: CO2 regulation for new vehicles - light | F37: In force | G37: Obligation | H37: 49.5 g of CO2/km for passenger cars & 90.6 g of CO2/km for delivery vans and light commercial vehicles in 2040 | I37: 49.5 g of CO2/km for passenger cars & 90.6 g of CO2/km for delivery vans and light commercial vehicles in 2035 | J37: 49.5 g of CO2/km for passenger cars & 90.6 g of CO2/km for delivery vans and light commercial vehicles in 2030 | K37: 25 g of CO2/km for passenger cars & 45 g of CO2/km for delivery vans and light commercial vehicles | L37: 0 g of CO2/km for passenger cars & 0 g of CO2/km for delivery vans and light commercial vehicles | AB37: 0.5 | AC37: 0.5
A38: I | B38: 36 | C38: 1-5 | D38: =A38 & "_" & B38 & "_" & C38 -> I_36_1-5 | E38: CO2 regulation for new vehicles - heavy | F38: In force | G38: Obligation | H38: 0.1 | I38: 0.2 | J38: must reduce average emissions by 30 per cent compared to the reference values set out in the EU regulation in 2030 | K38: 0.6 | L38: 1 | Z38: 0.5 | AA38: 0.5
A39: I | B39: 37 | C39: 1-5 | D39: =A39 & "_" & B39 & "_" & C39 -> I_37_1-5 | E39: Performance-related heavy vehicle fee (LSVA) - for the carriage of goods | F39: In force | G39: Obligation | H39: 20% lower emission factor | I39: 10% lower emission factor | J39: Relevant HVC weight (3.5t-40t) * Rate according to emission [I-Euro 0 to 5: 3.26 Rp/tkm; II: 2.82 Rp/tkm; III-Euro 6: 2.39 Rp/tkm] * Kilometres driven | K39: 10% higher emission factor | L39: 20% higher emission factor | Z39: 0.5 | AA39: 0.5
A40: I | B40: 38 | C40: 1-5 | D40: =A40 & "_" & B40 & "_" & C40 -> I_38_1-5 | E40: LSVA exemption/discount for heavy EV & FCEV | F40: In force | G40: Fiscal exemption | H40: no exemption and discount | I40: exemption and discount until 2029 | J40: exemption until 2029, discount until 2035 | K40: exemption until 2034, discount until 2040 | L40: exemption until 2039, discount until 2045 | Z40: 0.5 | AA40: 0.5 | AD40: Federal Council adopts dispatch on the further development of the HGV
A41: I | B41: 39 | C41: 1-5 | D41: =A41 & "_" & B41 & "_" & C41 -> I_39_1-5 | E41: Motor vehicle tax exemption for EV & FCEV | F41: In force | G41: Fiscal exemption | H41: 0-40% | I41: 0-80% | J41: varies between 0-100% across cantons | K41: 40-100% | L41: 80-100% | Z41: 0.25 | AA41: 0.25 | AB41: 0.25 | AC41: 0.25
A42: N | B42: 40 | C42: 4-5 | D42: =A42 & "_" & B42 & "_" & C42 -> N_40_4-5 | E42: Vehicle import tax exemption for FCEV | F42: Non-existent | G42: Fiscal exemption | H42: / | I42: / | J42: / | K42: 0.04 | L42: 0.06 | AA42: 0.5 | AC42: 0.5
A43: N | B43: 41 | C43: 4-5 | D43: =A43 & "_" & B43 & "_" & C43 -> N_41_4-5 | E43: subsidy on purchasing FCEV | F43: Non-existent | G43: Subsidy | H43: / | I43: / | J43: / | K43: 30% CAPEX | L43: 60% CAPEX | AA43: 0.5 | AC43: 0.5
A44: I | B44: 42 | C44: 1-5 | D44: =A44 & "_" & B44 & "_" & C44 -> I_42_1-5 | E44: subsidy on heavy EV charging infrastructure in small and medium-sized enterprises (SMEs) | F44: In force | G44: Subsidy | H44: up to 20% of the eligible costs | I44: up to 30% of the eligible costs | J44: up to 40% of the eligible costs | K44: up to 50% of the eligible costs | L44: up to 60% of the eligible costs | Z44: 1
A45: I | B45: 43 | C45: 1-5 | D45: =A45 & "_" & B45 & "_" & C45 -> I_43_1-5 | E45: subsidy on light EV charging infrastructure in residential or office facilities | F45: In force | G45: Subsidy | H45: 0-20% of the eligible costs, in most cantons around 10% | I45: 0-40% of the eligible costs, in most cantons around 20% | J45: 0-60% of the eligible costs, in most cantons around 30% | K45: 0-80% of the eligible costs, in most cantons around 40% | L45: 0-100% of the eligible costs, in most cantons around 50% | AB45: 1
A46: N | B46: 44 | C46: 4-5 | D46: =A46 & "_" & B46 & "_" & C46 -> N_44_4-5 | E46: subsidy on H2 filling stations | F46: Non-existent | G46: Subsidy | H46: / | I46: / | J46: / | K46: 30% CAPEX | L46: 60% CAPEX | AA46: 0.5 | AC46: 0.5
A47: N | B47: 45 | C47: 4-5 | D47: =A47 & "_" & B47 & "_" & C47 -> N_45_4-5 | E47: Ban on ICE vehicles | F47: Non-existent | G47: Ban | H47: / | I47: / | J47: / | K47: ban on the import of ICE vehicles | L47: ban on all ICE vechicles on the road | Z47: 0.25 | AA47: 0.25 | AB47: 0.25 | AC47: 0.25
A48: N | B48: 46 | C48: 4-5 | D48: =A48 & "_" & B48 & "_" & C48 -> N_46_4-5 | E48: subsidy on H2 for transport | F48: Non-existent | G48: Subsidy | H48: / | I48: / | J48: / | K48: 10% market price | L48: 30% market price | AA48: 0.5 | AC48: 0.5
D56: Policy selection and list principle
D57: 1. Only consider the policies that promote the technologies required in the 2050 energy system under the four scenarios. Policies that generally promote energy efficiency are not included in this analysis.
D58: Reason: Across the four scenarios, the final energy demand is very similar, which suggests that the level of energy efficiency is also expected to remain broadly comparable. Therefore, the current policy trend under the baseline scenario, EP2050+, can be considered sufficient to maintain the required level of energy efficiency without major policy adjustments. Furthermore, public awareness of energy use and energy saving in Switzerland is already relatively high, and behavioral change is not expected to be a key differentiating factor among the scenarios. For this reason, the analysis focuses only on policies that promote the development and deployment of new technologies required for achieving a net-zero energy system. These technologies are expected to expand at different levels across the four scenarios and lead to different energy system structures. By concentrating on technology-oriented policies, the analysis allows a clearer comparison between the three alternative scenarios and the baseline scenario EP2050+.
D59: 2. Policies are listed according to their inherent adjustment logic from the perspective of decision makers. This means that even if two policies share the same general name, they are treated as separate policies if they can be adjusted independently and target different technologies through these adjustments.
D60: Reason: In practice, policy makers often modify policy parameters, such as the level of support, eligibility rules, or targeted technologies, to guide the development of specific technologies. Therefore, separating these adjustable policy variants helps reflect how policies are actually designed and adapted in real decision-making processes. This approach also provides clearer information on which policy adjustments may be required to promote different technologies under each scenario.
D61: 3. Policies that only provide information to the public or companies are not included in the list.
D62: Reason: These policies are unlikely to change significantly in the future and usually do not directly or indirectly create incentives for the development or deployment of specific technologies. Therefore, they are not considered in this analysis, which focuses on policies that can actively promote the technologies required for the energy transition.
D63: 4. Policies that are only used to collect financial resources for other policies are not included in the list.
D64: Reason: These policies cannot function independently, because their role is only to raise funds, while the actual impact depends on how the money is used by other policy instruments. Therefore, they are not considered as direct measures that promote the energy transition in this analysis.

Sheet 2030-2040
A1: Policy ID | B1: Cost | C1: Effectiveness | D1: Acceptance of the tech. | E1: Acceptance of the policy instrument | F1: Administrative burden | G1: Positive Flow | H1: Negative Flow | I1: Net Flow
A2: I_01_1 | B2: 5 | C2: 2 | D2: 4 | E2: 4 | F2: 4
A3: I_01_2 | B3: 5 | C3: 3 | D3: 4 | E3: 3 | F3: 4
A4: I_01_3 | B4: 5 | C4: 4 | D4: 4 | E4: 2 | F4: 4
A5: I_01_4 | B5: 5 | C5: 5 | D5: 4 | E5: 1 | F5: 4
A6: I_01_5 | B6: 5 | C6: 5 | D6: 4 | E6: 1 | F6: 4
A7: N_02_4 | B7: 5 | C7: 2 | D7: 4 | E7: 2 | F7: 3
A8: N_02_5 | B8: 5 | C8: 3 | D8: 4 | E8: 1 | F8: 3
A9: I_03_1 | B9: 4 | C9: 2 | D9: 4 | E9: 4 | F9: 3
A10: I_03_2 | B10: 3 | C10: 3 | D10: 4 | E10: 4 | F10: 3
A11: I_03_3 | B11: 2 | C11: 4 | D11: 4 | E11: 4 | F11: 3
A12: I_04_3 | B12: 5 | C12: 1 | D12: 4 | E12: 4 | F12: 4
A13: I_04_4 | B13: 5 | C13: 3 | D13: 4 | E13: 3 | F13: 4
... A188: N_46_5 | B188: 2 | C188: 4 | D188: 4 | E188: 4 | F188: 3

Sheet 2040-2050
