Workbook

Sheet 2030-2040
A1: Policy ID | B1: Cost | C1: Effectiveness | D1: Acceptance of the tech. | E1: Acceptance of the policy instrument | F1: Administrative burden
A2: I_01_1 | B2: 5 | C2: 2 | D2: 4 | E2: 4 | F2: 4
A3: I_01_2 | B3: 5 | C3: 3 | D3: 4 | E3: 3 | F3: 4
A4: I_01_3 | B4: 5 | C4: 4 | D4: 4 | E4: 2 | F4: 4
A5: I_01_4 | B5: 5 | C5: 5 | D5: 4 | E5: 1 | F5: 4
A6: I_01_5 | B6: 5 | C6: 5 | D6: 4 | E6: 1 | F6: 4
A7: N_02_4 | B7: 5 | C7: 2 | D7: 4 | E7: 2 | F7: 3
A8: N_02_5 | B8: 5 | C8: 3 | D8: 4 | E8: 1 | F8: 3
A9: I_03_1 | B9: 4 | C9: 2 | D9: 4 | E9: 4 | F9: 3
A10: I_03_2 | B10: 3 | C10: 3 | D10: 4 | E10: 4 | F10: 3
A11: I_03_3 | B11: 2 | C11: 4 | D11: 4 | E11: 4 | F11: 3
A12: I_04_3 | B12: 5 | C12: 1 | D12: 4 | E12: 4 | F12: 4
A13: I_04_4 | B13: 5 | C13: 3 | D13: 4 | E13: 3 | F13: 4
... A188: N_46_5 | B188: 2 | C188: 4 | D188: 4 | E188: 4 | F188: 3

Sheet Criteria
B2: Cost (to Government): 1 = Extremely high fiscal burden/expense; 5 = Revenue generating or zero government cost.
B3: Effectiveness: 1 = Minimal technological deployment impact; 5 = Transformative, massive deployment driver.
B4: Acceptance of Technology: 1 = High public/political resistance; 5 = Broad, uncontroversial public support.
B5: Acceptance of Policy Instrument: 1 = Highly unpopular (e.g., steep new taxes/bans); 5 = Highly popular (e.g., voluntary subsidies).
B6: Administrative Burden: 1 = Highly complex, costly to manage; 5 = Simple, streamlined, or already seamlessly operational.
B10: Criterion | C10: Polarity | D10: Preference Function | E10: q | F10: p | G10: s | H10: Weight
B11: Cost | C11: Positive | D11: Type1 | H11: 0.2
B12: Effectiveness | C12: Positive | D12: Type1 | H12: 0.2
B13: Acceptance of the tech. | C13: Positive | D13: Type1 | H13: 0.2
B14: Acceptance of the policy instrument | C14: Positive | D14: Type1 | H14: 0.2
B15: Administrative burden | C15: Positive | D15: Type1 | H15: 0.2

Sheet Result
B1: Aggregated Score | C1: Aggregated Score | D1: Aggregated Score | E1: Cost | F1: Cost | G1: Cost | H1: Effectiveness | I1: Effectiveness | J1: Effectiveness | K1: Acceptance of the tech. | L1: Acceptance of the tech. | M1: Acceptance of the tech. | N1: Acceptance of the policy instrument | O1: Acceptance of the policy instrument | P1: Acceptance of the policy instrument | Q1: Administrative burden | R1: Administrative burden | S1: Administrative burden
A2: Alternative Name | B2: Positive Flow | C2: Negative Flow | D2: Net Flow | E2: Positive Flow | F2: Negative Flow | G2: Net Flow | H2: Positive Flow | I2: Negative Flow | J2: Net Flow | K2: Positive Flow | L2: Negative Flow | M2: Net Flow | N2: Positive Flow | O2: Negative Flow | P2: Net Flow | Q2: Positive Flow | R2: Negative Flow | S2: Net Flow
A3: I_11_3 | B3: 0.46666667 | C3: 0.12580645 | D3: 0.34086022 | E3: 0.31182796 | F3: 0.47849462 | G3: -0.16666667 | H3: 0.52688172 | I3: 0.15053763 | J3: 0.37634409 | K3: 0.52150538 | L3: 0 | M3: 0.52150538 | N3: 0.61827957 | O3: 0 | P3: 0.61827957 | Q3: 0.35483871 | R3: 0 | S3: 0.35483871
A4: I_16_3 | B4: 0.46666667 | C4: 0.12580645 | D4: 0.34086022 | E4: 0.31182796 | F4: 0.47849462 | G4: -0.16666667 | H4: 0.52688172 | I4: 0.15053763 | J4: 0.37634409 | K4: 0.52150538 | L4: 0 | M4: 0.52150538 | N4: 0.61827957 | O4: 0 | P4: 0.61827957 | Q4: 0.35483871 | R4: 0 | S4: 0.35483871
A5: I_26_3 | B5: 0.46666667 | C5: 0.12580645 | D5: 0.34086022 | E5: 0.31182796 | F5: 0.47849462 | G5: -0.16666667 | H5: 0.52688172 | I5: 0.15053763 | J5: 0.37634409 | K5: 0.52150538 | L5: 0 | M5: 0.52150538 | N5: 0.61827957 | O5: 0 | P5: 0.61827957 | Q5: 0.35483871 | R5: 0 | S5: 0.35483871
A6: I_27_4 | B6: 0.46666667 | C6: 0.12580645 | D6: 0.34086022 | E6: 0.31182796 | F6: 0.47849462 | G6: -0.16666667 | H6: 0.52688172 | I6: 0.15053763 | J6: 0.37634409 | K6: 0.52150538 | L6: 0 | M6: 0.52150538 | N6: 0.61827957 | O6: 0 | P6: 0.61827957 | Q6: 0.35483871 | R6: 0 | S6: 0.35483871
A7: I_43_3 | B7: 0.46666667 | C7: 0.12580645 | D7: 0.34086022 | E7: 0.31182796 | F7: 0.47849462 | G7: -0.16666667 | H7: 0.52688172 | I7: 0.15053763 | J7: 0.37634409 | K7: 0.52150538 | L7: 0 | M7: 0.52150538 | N7: 0.61827957 | O7: 0 | P7: 0.61827957 | Q7: 0.35483871 | R7: 0 | S7: 0.35483871
A8: I_35_5 | B8: 0.50967742 | C8: 0.17526882 | D8: 0.3344086 | E8: 0.77419355 | F8: 0 | G8: 0.77419355 | H8: 0.85483871 | I8: 0 | J8: 0.85483871 | K8: 0.52150538 | L8: 0 | M8: 0.52150538 | N8: 0.043010753 | O8: 0.87634409 | P8: -0.83333333 | Q8: 0.35483871 | R8: 0 | S8: 0.35483871
A9: I_36_5 | B9: 0.50967742 | C9: 0.17526882 | D9: 0.3344086 | E9: 0.77419355 | F9: 0 | G9: 0.77419355 | H9: 0.85483871 | I9: 0 | J9: 0.85483871 | K9: 0.52150538 | L9: 0 | M9: 0.52150538 | N9: 0.043010753 | O9: 0.87634409 | P9: -0.83333333 | Q9: 0.35483871 | R9: 0 | S9: 0.35483871
A10: I_16_2 | B10: 0.45376344 | C10: 0.14193548 | D10: 0.31182796 | E10: 0.52688172 | F10: 0.2311828 | G10: 0.29569892 | H10: 0.24731183 | I10: 0.47849462 | J10: -0.2311828 | K10: 0.52150538 | L10: 0 | M10: 0.52150538 | N10: 0.61827957 | O10: 0 | P10: 0.61827957 | Q10: 0.35483871 | R10: 0 | S10: 0.35483871
A11: I_27_2 | B11: 0.45376344 | C11: 0.14193548 | D11: 0.31182796 | E11: 0.52688172 | F11: 0.2311828 | G11: 0.29569892 | H11: 0.24731183 | I11: 0.47849462 | J11: -0.2311828 | K11: 0.52150538 | L11: 0 | M11: 0.52150538 | N11: 0.61827957 | O11: 0 | P11: 0.61827957 | Q11: 0.35483871 | R11: 0 | S11: 0.35483871
A12: I_42_2 | B12: 0.45376344 | C12: 0.14193548 | D12: 0.31182796 | E12: 0.52688172 | F12: 0.2311828 | G12: 0.29569892 | H12: 0.24731183 | I12: 0.47849462 | J12: -0.2311828 | K12: 0.52150538 | L12: 0 | M12: 0.52150538 | N12: 0.61827957 | O12: 0 | P12: 0.61827957 | Q12: 0.35483871 | R12: 0 | S12: 0.35483871
A13: I_43_2 | B13: 0.45376344 | C13: 0.14193548 | D13: 0.31182796 | E13: 0.52688172 | F13: 0.2311828 | G13: 0.29569892 | H13: 0.24731183 | I13: 0.47849462 | J13: -0.2311828 | K13: 0.52150538 | L13: 0 | M13: 0.52150538 | N13: 0.61827957 | O13: 0 | P13: 0.61827957 | Q13: 0.35483871 | R13: 0 | S13: 0.35483871
A14: I_09_5 | B14: 0.46989247 | C14: 0.17204301 | D14: 0.29784946 | E14: 0 | F14: 0.86021505 | G14: -0.86021505 | H14: 0.85483871 | I14: 0 | J14: 0.85483871 | K14: 0.52150538 | L14: 0 | M14: 0.52150538 | N14: 0.61827957 | O14: 0 | P14: 0.61827957 | Q14: 0.35483871 | R14: 0 | S14: 0.35483871
... A189: I_28_4 | B189: 0.13333333 | C189: 0.62258065 | D189: -0.48924731 | E189: 0.14516129 | F189: 0.69354839 | G189: -0.5483871 | H189: 0.24731183 | I189: 0.47849462 | J189: -0.2311828 | K189: 0 | L189: 0.90322581 | M189: -0.90322581 | N189: 0.19892473 | O189: 0.38709677 | P189: -0.18817204 | Q189: 0.075268817 | R189: 0.65053763 | S189: -0.57526882

Sheet data preparation
D1: Alternative Name | E1: Net Flow | F1: Adjusted Net Flow | G1: Biomass Boiler | H1: Heat Pump | I1: Methane Boiler | J1: CCGT (Ren. Methane) | K1: CHP (waste) | L1: CHP (Ren. Methane) | M1: Hydro (reservoir) | N1: Hydro (run of) | O1: PV (Roof) | P1: Pumped Hydro | Q1: Wind | R1: CCGT (Nat Gas) with DACCS | S1: Alpine PV | T1: Heavy EV | U1: Heavy FCEV | V1: Light EV | W1: Light FCEV
A2: I | B2: 1 | C2: 4 | D2: I_01_4 | E2: 0.13763441 | F2: =E2-$E$121 -> 0.62688172 | G2: 0.2 | H2: 0.2 | I2: 0.2 | K2: 0.2 | L2: 0.2
A3: I | B3: 1 | C3: 5 | D3: I_01_5 | E3: 0.13763441 | F3: =E3-$E$121 -> 0.62688172 | G3: 0.2 | H3: 0.2 | I3: 0.2 | K3: 0.2 | L3: 0.2
A4: I | B4: 1 | C4: 3 | D4: I_01_3 | E4: 0.067741935 | F4: =E4-$E$121 -> 0.55698925 | G4: 0.2 | H4: 0.2 | I4: 0.2 | K4: 0.2 | L4: 0.2
A5: I | B5: 1 | C5: 2 | D5: I_01_2 | E5: -0.022580645 | F5: =E5-$E$121 -> 0.46666667 | G5: 0.2 | H5: 0.2 | I5: 0.2 | K5: 0.2 | L5: 0.2
A6: I | B6: 1 | C6: 1 | D6: I_01_1 | E6: -0.027956989 | F6: =E6-$E$121 -> 0.46129032 | G6: 0.2 | H6: 0.2 | I6: 0.2 | K6: 0.2 | L6: 0.2
A7: N | B7: 2 | C7: 5 | D7: N_02_5 | E7: -0.2655914 | F7: =E7-$E$121 -> 0.22365591 | T7: 0.25 | U7: 0.25 | V7: 0.25 | W7: 0.25
A8: N | B8: 2 | C8: 4 | D8: N_02_4 | E8: -0.34301075 | F8: =E8-$E$121 -> 0.14623656 | T8: 0.25 | U8: 0.25 | V8: 0.25 | W8: 0.25
A9: I | B9: 3 | C9: 3 | D9: I_03_3 | E9: -0.25376344 | F9: =E9-$E$121 -> 0.23548387 | L9: 1
A10: I | B10: 3 | C10: 2 | D10: I_03_2 | E10: -0.29892473 | F10: =E10-$E$121 -> 0.19032258 | L10: 1
A11: I | B11: 3 | C11: 1 | D11: I_03_1 | E11: -0.30967742 | F11: =E11-$E$121 -> 0.17956989 | L11: 1
A12: I | B12: 4 | C12: 5 | D12: I_04_5 | E12: 0.067741935 | F12: =E12-$E$121 -> 0.55698925 | G12: 0.2 | H12: 0.2 | I12: 0.2 | K12: 0.2 | L12: 0.2
A13: I | B13: 4 | C13: 4 | D13: I_04_4 | E13: -0.022580645 | F13: =E13-$E$121 -> 0.46666667 | G13: 0.2 | H13: 0.2 | I13: 0.2 | K13: 0.2 | L13: 0.2
A14: I | B14: 4 | C14: 3 | D14: I_04_3 | E14: -0.077419355 | F14: =E14-$E$121 -> 0.41182796 | G14: 0.2 | H14: 0.2 | I14: 0.2 | K14: 0.2 | L14: 0.2
A15: I | B15: 5 | C15: 5 | D15: I_05_5 | E15: 0.13763441 | F15: =E15-$E$121 -> 0.62688172 | T15: 0.25 | U15: 0.25 | V15: 0.25 | W15: 0.25
A16: I | B16: 5 | C16: 4 | D16: I_05_4 | E16: 0.041935484 | F16: =E16-$E$121 -> 0.5311828 | T16: 0.25 | U16: 0.25 | V16: 0.25 | W16: 0.25
A17: I | B17: 5 | C17: 2 | D17: I_05_2 | E17: -0.053763441 | F17: =E17-$E$121 -> 0.43548387 | T17: 0.25 | U17: 0.25 | V17: 0.25 | W17: 0.25
A18: I | B18: 5 | C18: 3 | D18: I_05_3 | E18: -0.053763441 | F18: =E18-$E$121 -> 0.43548387 | T18: 0.25 | U18: 0.25 | V18: 0.25 | W18: 0.25
A19: I | B19: 5 | C19: 1 | D19: I_05_1 | E19: -0.12580645 | F19: =E19-$E$121 -> 0.36344086 | T19: 0.25 | U19: 0.25 | V19: 0.25 | W19: 0.25
A20: I | B20: 6 | C20: 4 | D20: I_06_4 | E20: 0.16344086 | F20: =E20-$E$121 -> 0.65268817 | J20: 0.1 | K20: 0.1 | L20: 0.1 | M20: 0.1 | N20: 0.1 | O20: 0.1 | P20: 0.1 | Q20: 0.1 | R20: 0.1 | S20: 0.1
A21: I | B21: 6 | C21: 5 | D21: I_06_5 | E21: 0.16344086 | F21: =E21-$E$121 -> 0.65268817 | J21: 0.1 | K21: 0.1 | L21: 0.1 | M21: 0.1 | N21: 0.1 | O21: 0.1 | P21: 0.1 | Q21: 0.1 | R21: 0.1 | S21: 0.1
A22: I | B22: 6 | C22: 2 | D22: I_06_2 | E22: 0.098924731 | F22: =E22-$E$121 -> 0.58817204 | J22: 0.1 | K22: 0.1 | L22: 0.1 | M22: 0.1 | N22: 0.1 | O22: 0.1 | P22: 0.1 | Q22: 0.1 | R22: 0.1 | S22: 0.1
A23: I | B23: 6 | C23: 3 | D23: I_06_3 | E23: 0.098924731 | F23: =E23-$E$121 -> 0.58817204 | J23: 0.1 | K23: 0.1 | L23: 0.1 | M23: 0.1 | N23: 0.1 | O23: 0.1 | P23: 0.1 | Q23: 0.1 | R23: 0.1 | S23: 0.1
A24: I | B24: 6 | C24: 1 | D24: I_06_1 | E24: 0.075268817 | F24: =E24-$E$121 -> 0.56451613 | J24: 0.1 | K24: 0.1 | L24: 0.1 | M24: 0.1 | N24: 0.1 | O24: 0.1 | P24: 0.1 | Q24: 0.1 | R24: 0.1 | S24: 0.1
A25: N | B25: 7 | C25: 5 | D25: N_07_5 | E25: -0.37419355 | F25: =E25-$E$121 -> 0.11505376 | R25: 1
A26: N | B26: 7 | C26: 4 | D26: N_07_4 | E26: -0.46774194 | F26: =E26-$E$121 -> 0.021505376 | R26: 1
A27: N | B27: 8 | C27: 4 | D27: N_08_4 | E27: -0.46236559 | F27: =E27-$E$121 -> 0.02688172 | R27: 1
A28: N | B28: 8 | C28: 5 | D28: N_08_5 | E28: -0.47956989 | F28: =E28-$E$121 -> 0.0096774194 | R28: 1
A29: I | B29: 9 | C29: 5 | D29: I_09_5 | E29: 0.29784946 | F29: =E29-$E$121 -> 0.78709677 | G29: 0.25 | H29: 0.25 | K29: 0.25 | L29: 0.25
A30: I | B30: 9 | C30: 4 | D30: I_09_4 | E30: 0.26451613 | F30: =E30-$E$121 -> 0.75376344 | G30: 0.25 | H30: 0.25 | K30: 0.25 | L30: 0.25
A31: I | B31: 9 | C31: 3 | D31: I_09_3 | E31: 0.21935484 | F31: =E31-$E$121 -> 0.70860215 | G31: 0.25 | H31: 0.25 | K31: 0.25 | L31: 0.25
A32: I | B32: 9 | C32: 1 | D32: I_09_1 | E32: 0.20860215 | F32: =E32-$E$121 -> 0.69784946 | G32: 0.25 | H32: 0.25 | K32: 0.25 | L32: 0.25
A33: I | B33: 9 | C33: 2 | D33: I_09_2 | E33: 0.20860215 | F33: =E33-$E$121 -> 0.69784946 | G33: 0.25 | H33: 0.25 | K33: 0.25 | L33: 0.25
A34: I | B34: 10 | C34: 5 | D34: I_10_5 | E34: 0.29784946 | F34: =E34-$E$121 -> 0.78709677 | G34: 0.2 | H34: 0.2 | I34: 0.2 | K34: 0.2 | L34: 0.2
A35: I | B35: 10 | C35: 4 | D35: I_10_4 | E35: 0.26451613 | F35: =E35-$E$121 -> 0.75376344 | G35: 0.2 | H35: 0.2 | I35: 0.2 | K35: 0.2 | L35: 0.2
A36: I | B36: 10 | C36: 3 | D36: I_10_3 | E36: 0.21935484 | F36: =E36-$E$121 -> 0.70860215 | G36: 0.2 | H36: 0.2 | I36: 0.2 | K36: 0.2 | L36: 0.2
A37: I | B37: 10 | C37: 1 | D37: I_10_1 | E37: 0.20860215 | F37: =E37-$E$121 -> 0.69784946 | G37: 0.2 | H37: 0.2 | I37: 0.2 | K37: 0.2 | L37: 0.2
A38: I | B38: 10 | C38: 2 | D38: I_10_2 | E38: 0.20860215 | F38: =E38-$E$121 -> 0.69784946 | G38: 0.2 | H38: 0.2 | I38: 0.2 | K38: 0.2 | L38: 0.2
A39: I | B39: 11 | C39: 3 | D39: I_11_3 | E39: 0.34086022 | F39: =E39-$E$121 -> 0.83010753 | H39: 1
A40: I | B40: 11 | C40: 5 | D40: I_11_5 | E40: 0.29784946 | F40: =E40-$E$121 -> 0.78709677 | H40: 1
A41: I | B41: 11 | C41: 4 | D41: I_11_4 | E41: 0.26451613 | F41: =E41-$E$121 -> 0.75376344 | H41: 1
A42: I | B42: 11 | C42: 1 | D42: I_11_1 | E42: 0.20860215 | F42: =E42-$E$121 -> 0.69784946 | H42: 1
A43: I | B43: 11 | C43: 2 | D43: I_11_2 | E43: 0.20860215 | F43: =E43-$E$121 -> 0.69784946 | H43: 1
A44: I | B44: 12 | C44: 4 | D44: I_12_4 | E44: 0.093548387 | F44: =E44-$E$121 -> 0.5827957 | G44: 1
A45: I | B45: 12 | C45: 3 | D45: I_12_3 | E45: 0.048387097 | F45: =E45-$E$121 -> 0.53763441 | G45: 1
A46: I | B46: 12 | C46: 1 | D46: I_12_1 | E46: 0.037634409 | F46: =E46-$E$121 -> 0.52688172 | G46: 1
A47: I | B47: 12 | C47: 2 | D47: I_12_2 | E47: 0.037634409 | F47: =E47-$E$121 -> 0.52688172 | G47: 1
A48: I | B48: 12 | C48: 5 | D48: I_12_5 | E48: 0.031182796 | F48: =E48-$E$121 -> 0.52043011 | G48: 1
A49: I | B49: 13 | C49: 5 | D49: I_13_5 | E49: -0.048387097 | F49: =E49-$E$121 -> 0.44086022 | G49: 0.2 | H49: 0.2 | I49: 0.2 | K49: 0.2 | L49: 0.2
A50: I | B50: 13 | C50: 4 | D50: I_13_4 | E50: -0.11827957 | F50: =E50-$E$121 -> 0.37096774 | G50: 0.2 | H50: 0.2 | I50: 0.2 | K50: 0.2 | L50: 0.2
A51: I | B51: 13 | C51: 3 | D51: I_13_3 | E51: -0.20860215 | F51: =E51-$E$121 -> 0.28064516 | G51: 0.2 | H51: 0.2 | I51: 0.2 | K51: 0.2 | L51: 0.2
A52: I | B52: 14 | C52: 5 | D52: I_14_5 | E52: -0.016129032 | F52: =E52-$E$121 -> 0.47311828 | J52: 0.1 | K52: 0.1 | L52: 0.1 | M52: 0.1 | N52: 0.1 | O52: 0.1 | P52: 0.1 | Q52: 0.1 | R52: 0.1 | S52: 0.1
A53: I | B53: 14 | C53: 4 | D53: I_14_4 | E53: -0.10645161 | F53: =E53-$E$121 -> 0.3827957 | J53: 0.1 | K53: 0.1 | L53: 0.1 | M53: 0.1 | N53: 0.1 | O53: 0.1 | P53: 0.1 | Q53: 0.1 | R53: 0.1 | S53: 0.1
A54: I | B54: 14 | C54: 3 | D54: I_14_3 | E54: -0.11182796 | F54: =E54-$E$121 -> 0.37741935 | J54: 0.1 | K54: 0.1 | L54: 0.1 | M54: 0.1 | N54: 0.1 | O54: 0.1 | P54: 0.1 | Q54: 0.1 | R54: 0.1 | S54: 0.1
A55: I | B55: 15 | C55: 4 | D55: I_15_4 | E55: 0.093548387 | F55: =E55-$E$121 -> 0.5827957 | K55: 0.5 | L55: 0.5
A56: I | B56: 15 | C56: 3 | D56: I_15_3 | E56: 0.048387097 | F56: =E56-$E$121 -> 0.53763441 | K56: 0.5 | L56: 0.5
A57: I | B57: 15 | C57: 1 | D57: I_15_1 | E57: 0.037634409 | F57: =E57-$E$121 -> 0.52688172 | K57: 0.5 | L57: 0.5
A58: I | B58: 15 | C58: 2 | D58: I_15_2 | E58: 0.037634409 | F58: =E58-$E$121 -> 0.52688172 | K58: 0.5 | L58: 0.5
A59: I | B59: 15 | C59: 5 | D59: I_15_5 | E59: 0.031182796 | F59: =E59-$E$121 -> 0.52043011 | K59: 0.5 | L59: 0.5
A60: I | B60: 16 | C60: 3 | D60: I_16_3 | E60: 0.34086022 | F60: =E60-$E$121 -> 0.83010753 | O60: 0.5 | S60: 0.5
A61: I | B61: 16 | C61: 2 | D61: I_16_2 | E61: 0.31182796 | F61: =E61-$E$121 -> 0.80107527 | O61: 0.5 | S61: 0.5
A62: I | B62: 16 | C62: 5 | D62: I_16_5 | E62: 0.29784946 | F62: =E62-$E$121 -> 0.78709677 | O62: 0.5 | S62: 0.5
A63: I | B63: 16 | C63: 4 | D63: I_16_4 | E63: 0.26451613 | F63: =E63-$E$121 -> 0.75376344 | O63: 0.5 | S63: 0.5
A64: I | B64: 16 | C64: 1 | D64: I_16_1 | E64: 0.20860215 | F64: =E64-$E$121 -> 0.69784946 | O64: 0.5 | S64: 0.5
A65: I | B65: 17 | C65: 4 | D65: I_17_4 | E65: 0.012903226 | F65: =E65-$E$121 -> 0.50215054 | O65: 0.5 | S65: 0.5
A66: I | B66: 17 | C66: 2 | D66: I_17_2 | E66: -0.0064516129 | F66: =E66-$E$121 -> 0.4827957 | O66: 0.5 | S66: 0.5
A67: I | B67: 17 | C67: 1 | D67: I_17_1 | E67: -0.035483871 | F67: =E67-$E$121 -> 0.45376344 | O67: 0.5 | S67: 0.5
A68: I | B68: 17 | C68: 5 | D68: I_17_5 | E68: -0.049462366 | F68: =E68-$E$121 -> 0.43978495 | O68: 0.5 | S68: 0.5
A69: I | B69: 17 | C69: 3 | D69: I_17_3 | E69: -0.082795699 | F69: =E69-$E$121 -> 0.40645161 | O69: 0.5 | S69: 0.5
A70: I | B70: 18 | C70: 3 | D70: I_18_3 | E70: -0.0064516129 | F70: =E70-$E$121 -> 0.4827957 | O70: 0.5 | S70: 0.5
A71: I | B71: 18 | C71: 2 | D71: I_18_2 | E71: -0.035483871 | F71: =E71-$E$121 -> 0.45376344 | O71: 0.5 | S71: 0.5
... A84: I | B84: 20 | C84: 2 | D84: I_20_2 | E84: 0.047311828 | F84: =E84-$E$121 -> 0.53655914 | O84: 0.5 | S84: 0.5
A85: N | B85: 21 | C85: 4 | D85: N_21_4 | E85: -0.32580645 | F85: =E85-$E$121 -> 0.16344086 | S85: 1
A86: N | B86: 21 | C86: 5 | D86: N_21_5 | E86: -0.3688172 | F86: =E86-$E$121 -> 0.12043011 | S86: 1
A87: I | B87: 22 | C87: 4 | D87: I_22_4 | E87: -0.25376344 | F87: =E87-$E$121 -> 0.23548387 | J87: 0.5 | L87: 0.5
A88: I | B88: 22 | C88: 3 | D88: I_22_3 | E88: -0.29892473 | F88: =E88-$E$121 -> 0.19032258 | J88: 0.5 | L88: 0.5
A89: I | B89: 22 | C89: 1 | D89: I_22_1 | E89: -0.30967742 | F89: =E89-$E$121 -> 0.17956989 | J89: 0.5 | L89: 0.5
A90: I | B90: 22 | C90: 2 | D90: I_22_2 | E90: -0.30967742 | F90: =E90-$E$121 -> 0.17956989 | J90: 0.5 | L90: 0.5
A91: I | B91: 22 | C91: 5 | D91: I_22_5 | E91: -0.31612903 | F91: =E91-$E$121 -> 0.17311828 | J91: 0.5 | L91: 0.5
A92: I | B92: 23 | C92: 4 | D92: I_23_4 | E92: -0.067741935 | F92: =E92-$E$121 -> 0.42150538 | J92: 0.5 | L92: 0.5
A93: I | B93: 23 | C93: 3 | D93: I_23_3 | E93: -0.11290323 | F93: =E93-$E$121 -> 0.37634409 | J93: 0.5 | L93: 0.5
A94: I | B94: 23 | C94: 1 | D94: I_23_1 | E94: -0.12365591 | F94: =E94-$E$121 -> 0.3655914 | J94: 0.5 | L94: 0.5
A95: I | B95: 23 | C95: 2 | D95: I_23_2 | E95: -0.12365591 | F95: =E95-$E$121 -> 0.3655914 | J95: 0.5 | L95: 0.5
A96: I | B96: 23 | C96: 5 | D96: I_23_5 | E96: -0.13010753 | F96: =E96-$E$121 -> 0.35913978 | J96: 0.5 | L96: 0.5
A97: I | B97: 24 | C97: 5 | D97: I_24_5 | E97: 0.12688172 | F97: =E97-$E$121 -> 0.61612903 | J97: 0.33 | K97: 0.33 | L97: 0.33
A98: I | B98: 24 | C98: 3 | D98: I_24_3 | E98: 0.093548387 | F98: =E98-$E$121 -> 0.5827957 | J98: 0.33 | K98: 0.33 | L98: 0.33
A99: I | B99: 24 | C99: 4 | D99: I_24_4 | E99: 0.093548387 | F99: =E99-$E$121 -> 0.5827957 | J99: 0.33 | K99: 0.33 | L99: 0.33
A100: I | B100: 24 | C100: 2 | D100: I_24_2 | E100: 0.048387097 | F100: =E100-$E$121 -> 0.53763441 | J100: 0.33 | K100: 0.33 | L100: 0.33
A101: I | B101: 24 | C101: 1 | D101: I_24_1 | E101: 0.037634409 | F101: =E101-$E$121 -> 0.52688172 | J101: 0.33 | K101: 0.33 | L101: 0.33
A102: I | B102: 25 | C102: 4 | D102: I_25_4 | E102: -0.082795699 | F102: =E102-$E$121 -> 0.40645161 | M102: 0.33 | N102: 0.33 | P102: 0.33
A103: I | B103: 25 | C103: 3 | D103: I_25_3 | E103: -0.12795699 | F103: =E103-$E$121 -> 0.36129032 | M103: 0.33 | N103: 0.33 | P103: 0.33
A104: I | B104: 25 | C104: 1 | D104: I_25_1 | E104: -0.13870968 | F104: =E104-$E$121 -> 0.35053763 | M104: 0.33 | N104: 0.33 | P104: 0.33
A105: I | B105: 25 | C105: 2 | D105: I_25_2 | E105: -0.13870968 | F105: =E105-$E$121 -> 0.35053763 | M105: 0.33 | N105: 0.33 | P105: 0.33
A106: I | B106: 25 | C106: 5 | D106: I_25_5 | E106: -0.14516129 | F106: =E106-$E$121 -> 0.34408602 | M106: 0.33 | N106: 0.33 | P106: 0.33
A107: I | B107: 26 | C107: 3 | D107: I_26_3 | E107: 0.34086022 | F107: =E107-$E$121 -> 0.83010753 | M107: 0.33 | N107: 0.33 | P107: 0.33
A108: I | B108: 26 | C108: 5 | D108: I_26_5 | E108: 0.29784946 | F108: =E108-$E$121 -> 0.78709677 | M108: 0.33 | N108: 0.33 | P108: 0.33
A109: I | B109: 26 | C109: 4 | D109: I_26_4 | E109: 0.26451613 | F109: =E109-$E$121 -> 0.75376344 | M109: 0.33 | N109: 0.33 | P109: 0.33
A110: I | B110: 26 | C110: 2 | D110: I_26_2 | E110: 0.21935484 | F110: =E110-$E$121 -> 0.70860215 | M110: 0.33 | N110: 0.33 | P110: 0.33
A111: I | B111: 26 | C111: 1 | D111: I_26_1 | E111: 0.20860215 | F111: =E111-$E$121 -> 0.69784946 | M111: 0.33 | N111: 0.33 | P111: 0.33
A112: I | B112: 27 | C112: 4 | D112: I_27_4 | E112: 0.34086022 | F112: =E112-$E$121 -> 0.83010753 | M112: 0.33 | N112: 0.33 | P112: 0.33
...

Sheet Tech. Support level
D1: Alternative Name | E1: Net Flow | F1: Adjusted Net Flow | G1: Biomass Boiler | H1: Heat Pump | I1: Methane Boiler | J1: CCGT (Ren. Methane) | K1: CHP (waste) | L1: CHP (Ren. Methane) | M1: Hydro (reservoir) | N1: Hydro (run of) | O1: PV (Roof) | P1: Pumped Hydro | Q1: Wind | R1: CCGT (Nat Gas) with DACCS | S1: Alpine PV | T1: Heavy EV | U1: Heavy FCEV | V1: Light EV | W1: Light FCEV | X1: Biomass Boiler | Y1: Heat Pump | Z1: Methane Boiler | AA1: CCGT (Ren. Methane) | AB1: CHP (waste) | AC1: CHP (Ren. Methane) | AD1: Hydro (reservoir) | AE1: Hydro (run of) | AF1: PV (Roof) | AG1: Pumped Hydro | AH1: Wind | AI1: CCGT (Nat Gas) with DACCS | AJ1: Alpine PV | AK1: Heavy EV | AL1: Heavy FCEV | AM1: Light EV | AN1: Light FCEV
A2: I | B2: 1 | C2: 4 | D2: I_01_4 | E2: 0.13763441 | F2: =E2-$E$121 -> 0.62688172 | G2: 0.2 | H2: 0.2 | I2: 0.2 | K2: 0.2 | L2: 0.2 | X2: =$F2*G2 -> 0.12537634 | Y2: =$F2*H2 -> 0.12537634 | Z2: =$F2*I2 -> 0.12537634 | AA2: =$F2*J2 -> 0 | AB2: =$F2*K2 -> 0.12537634 | AC2: =$F2*L2 -> 0.12537634 | AD2: =$F2*M2 -> 0 | AE2: =$F2*N2 -> 0 | ... AN2: =$F2*W2 -> 0
A3: I | B3: 1 | C3: 5 | D3: I_01_5 | E3: 0.13763441 | F3: =E3-$E$121 -> 0.62688172 | G3: 0.2 | H3: 0.2 | I3: 0.2 | K3: 0.2 | L3: 0.2 | X3: =$F3*G3 -> 0.12537634 | Y3: =$F3*H3 -> 0.12537634 | Z3: =$F3*I3 -> 0.12537634 | AA3: =$F3*J3 -> 0 | AB3: =$F3*K3 -> 0.12537634 | AC3: =$F3*L3 -> 0.12537634 | AD3: =$F3*M3 -> 0 | AE3: =$F3*N3 -> 0 | ... AN3: =$F3*W3 -> 0
A4: I | B4: 1 | C4: 3 | D4: I_01_3 | E4: 0.067741935 | F4: =E4-$E$121 -> 0.55698925 | G4: 0.2 | H4: 0.2 | I4: 0.2 | K4: 0.2 | L4: 0.2 | X4: =$F4*G4 -> 0.11139785 | Y4: =$F4*H4 -> 0.11139785 | Z4: =$F4*I4 -> 0.11139785 | AA4: =$F4*J4 -> 0 | AB4: =$F4*K4 -> 0.11139785 | AC4: =$F4*L4 -> 0.11139785 | AD4: =$F4*M4 -> 0 | AE4: =$F4*N4 -> 0 | ... AN4: =$F4*W4 -> 0
A5: I | B5: 1 | C5: 2 | D5: I_01_2 | E5: -0.022580645 | F5: =E5-$E$121 -> 0.46666667 | G5: 0.2 | H5: 0.2 | I5: 0.2 | K5: 0.2 | L5: 0.2 | X5: =$F5*G5 -> 0.093333333 | Y5: =$F5*H5 -> 0.093333333 | Z5: =$F5*I5 -> 0.093333333 | AA5: =$F5*J5 -> 0 | AB5: =$F5*K5 -> 0.093333333 | AC5: =$F5*L5 -> 0.093333333 | AD5: =$F5*M5 -> 0 | AE5: =$F5*N5 -> 0 | ... AN5: =$F5*W5 -> 0
A6: I | B6: 1 | C6: 1 | D6: I_01_1 | E6: -0.027956989 | F6: =E6-$E$121 -> 0.46129032 | G6: 0.2 | H6: 0.2 | I6: 0.2 | K6: 0.2 | L6: 0.2 | X6: =$F6*G6 -> 0.092258065 | Y6: =$F6*H6 -> 0.092258065 | Z6: =$F6*I6 -> 0.092258065 | AA6: =$F6*J6 -> 0 | AB6: =$F6*K6 -> 0.092258065 | AC6: =$F6*L6 -> 0.092258065 | AD6: =$F6*M6 -> 0 | AE6: =$F6*N6 -> 0 | ... AN6: =$F6*W6 -> 0
A7: N | B7: 2 | C7: 5 | D7: N_02_5 | E7: -0.2655914 | F7: =E7-$E$121 -> 0.22365591 | T7: 0.25 | U7: 0.25 | V7: 0.25 | W7: 0.25 | X7: =$F7*G7 -> 0 | Y7: =$F7*H7 -> 0 | Z7: =$F7*I7 -> 0 | AA7: =$F7*J7 -> 0 | AB7: =$F7*K7 -> 0 | AC7: =$F7*L7 -> 0 | AD7: =$F7*M7 -> 0 | AE7: =$F7*N7 -> 0 | ... AN7: =$F7*W7 -> 0.055913978
A8: N | B8: 2 | C8: 4 | D8: N_02_4 | E8: -0.34301075 | F8: =E8-$E$121 -> 0.14623656 | T8: 0.25 | U8: 0.25 | V8: 0.25 | W8: 0.25 | X8: =$F8*G8 -> 0 | Y8: =$F8*H8 -> 0 | Z8: =$F8*I8 -> 0 | AA8: =$F8*J8 -> 0 | AB8: =$F8*K8 -> 0 | AC8: =$F8*L8 -> 0 | AD8: =$F8*M8 -> 0 | AE8: =$F8*N8 -> 0 | ... AN8: =$F8*W8 -> 0.03655914
A9: I | B9: 3 | C9: 3 | D9: I_03_3 | E9: -0.25376344 | F9: =E9-$E$121 -> 0.23548387 | L9: 1 | X9: =$F9*G9 -> 0 | Y9: =$F9*H9 -> 0 | Z9: =$F9*I9 -> 0 | AA9: =$F9*J9 -> 0 | AB9: =$F9*K9 -> 0 | AC9: =$F9*L9 -> 0.23548387 | AD9: =$F9*M9 -> 0 | AE9: =$F9*N9 -> 0 | ... AN9: =$F9*W9 -> 0
A10: I | B10: 3 | C10: 2 | D10: I_03_2 | E10: -0.29892473 | F10: =E10-$E$121 -> 0.19032258 | L10: 1 | X10: =$F10*G10 -> 0 | Y10: =$F10*H10 -> 0 | Z10: =$F10*I10 -> 0 | AA10: =$F10*J10 -> 0 | AB10: =$F10*K10 -> 0 | AC10: =$F10*L10 -> 0.19032258 | AD10: =$F10*M10 -> 0 | AE10: =$F10*N10 -> 0 | ... AN10: =$F10*W10 -> 0
A11: I | B11: 3 | C11: 1 | D11: I_03_1 | E11: -0.30967742 | F11: =E11-$E$121 -> 0.17956989 | L11: 1 | X11: =$F11*G11 -> 0 | Y11: =$F11*H11 -> 0 | Z11: =$F11*I11 -> 0 | AA11: =$F11*J11 -> 0 | AB11: =$F11*K11 -> 0 | AC11: =$F11*L11 -> 0.17956989 | AD11: =$F11*M11 -> 0 | AE11: =$F11*N11 -> 0 | ... AN11: =$F11*W11 -> 0
A12: I | B12: 4 | C12: 5 | D12: I_04_5 | E12: 0.067741935 | F12: =E12-$E$121 -> 0.55698925 | G12: 0.2 | H12: 0.2 | I12: 0.2 | K12: 0.2 | L12: 0.2 | X12: =$F12*G12 -> 0.11139785 | Y12: =$F12*H12 -> 0.11139785 | Z12: =$F12*I12 -> 0.11139785 | AA12: =$F12*J12 -> 0 | AB12: =$F12*K12 -> 0.11139785 | AC12: =$F12*L12 -> 0.11139785 | AD12: =$F12*M12 -> 0 | AE12: =$F12*N12 -> 0 | ... AN12: =$F12*W12 -> 0
A13: I | B13: 4 | C13: 4 | D13: I_04_4 | E13: -0.022580645 | F13: =E13-$E$121 -> 0.46666667 | G13: 0.2 | H13: 0.2 | I13: 0.2 | K13: 0.2 | L13: 0.2 | X13: =$F13*G13 -> 0.093333333 | Y13: =$F13*H13 -> 0.093333333 | Z13: =$F13*I13 -> 0.093333333 | AA13: =$F13*J13 -> 0 | AB13: =$F13*K13 -> 0.093333333 | AC13: =$F13*L13 -> 0.093333333 | AD13: =$F13*M13 -> 0 | AE13: =$F13*N13 -> 0 | ... AN13: =$F13*W13 -> 0
A14: I | B14: 4 | C14: 3 | D14: I_04_3 | E14: -0.077419355 | F14: =E14-$E$121 -> 0.41182796 | G14: 0.2 | H14: 0.2 | I14: 0.2 | K14: 0.2 | L14: 0.2 | X14: =$F14*G14 -> 0.082365591 | Y14: =$F14*H14 -> 0.082365591 | Z14: =$F14*I14 -> 0.082365591 | AA14: =$F14*J14 -> 0 | AB14: =$F14*K14 -> 0.082365591 | AC14: =$F14*L14 -> 0.082365591 | AD14: =$F14*M14 -> 0 | AE14: =$F14*N14 -> 0 | ... AN14: =$F14*W14 -> 0
A15: I | B15: 5 | C15: 5 | D15: I_05_5 | E15: 0.13763441 | F15: =E15-$E$121 -> 0.62688172 | T15: 0.25 | U15: 0.25 | V15: 0.25 | W15: 0.25 | X15: =$F15*G15 -> 0 | Y15: =$F15*H15 -> 0 | Z15: =$F15*I15 -> 0 | AA15: =$F15*J15 -> 0 | AB15: =$F15*K15 -> 0 | AC15: =$F15*L15 -> 0 | AD15: =$F15*M15 -> 0 | AE15: =$F15*N15 -> 0 | ... AN15: =$F15*W15 -> 0.15672043
A16: I | B16: 5 | C16: 4 | D16: I_05_4 | E16: 0.041935484 | F16: =E16-$E$121 -> 0.5311828 | T16: 0.25 | U16: 0.25 | V16: 0.25 | W16: 0.25 | X16: =$F16*G16 -> 0 | Y16: =$F16*H16 -> 0 | Z16: =$F16*I16 -> 0 | AA16: =$F16*J16 -> 0 | AB16: =$F16*K16 -> 0 | AC16: =$F16*L16 -> 0 | AD16: =$F16*M16 -> 0 | AE16: =$F16*N16 -> 0 | ... AN16: =$F16*W16 -> 0.1327957
A17: I | B17: 5 | C17: 2 | D17: I_05_2 | E17: -0.053763441 | F17: =E17-$E$121 -> 0.43548387 | T17: 0.25 | U17: 0.25 | V17: 0.25 | W17: 0.25 | X17: =$F17*G17 -> 0 | Y17: =$F17*H17 -> 0 | Z17: =$F17*I17 -> 0 | AA17: =$F17*J17 -> 0 | AB17: =$F17*K17 -> 0 | AC17: =$F17*L17 -> 0 | AD17: =$F17*M17 -> 0 | AE17: =$F17*N17 -> 0 | ... AN17: =$F17*W17 -> 0.10887097
A18: I | B18: 5 | C18: 3 | D18: I_05_3 | E18: -0.053763441 | F18: =E18-$E$121 -> 0.43548387 | T18: 0.25 | U18: 0.25 | V18: 0.25 | W18: 0.25 | X18: =$F18*G18 -> 0 | Y18: =$F18*H18 -> 0 | Z18: =$F18*I18 -> 0 | AA18: =$F18*J18 -> 0 | AB18: =$F18*K18 -> 0 | AC18: =$F18*L18 -> 0 | AD18: =$F18*M18 -> 0 | AE18: =$F18*N18 -> 0 | ... AN18: =$F18*W18 -> 0.10887097
A19: I | B19: 5 | C19: 1 | D19: I_05_1 | E19: -0.12580645 | F19: =E19-$E$121 -> 0.36344086 | T19: 0.25 | U19: 0.25 | V19: 0.25 | W19: 0.25 | X19: =$F19*G19 -> 0 | Y19: =$F19*H19 -> 0 | Z19: =$F19*I19 -> 0 | AA19: =$F19*J19 -> 0 | AB19: =$F19*K19 -> 0 | AC19: =$F19*L19 -> 0 | AD19: =$F19*M19 -> 0 | AE19: =$F19*N19 -> 0 | ... AN19: =$F19*W19 -> 0.090860215
A20: I | B20: 6 | C20: 4 | D20: I_06_4 | E20: 0.16344086 | F20: =E20-$E$121 -> 0.65268817 | J20: 0.1 | K20: 0.1 | L20: 0.1 | M20: 0.1 | N20: 0.1 | O20: 0.1 | P20: 0.1 | Q20: 0.1 | R20: 0.1 | S20: 0.1 | X20: =$F20*G20 -> 0 | Y20: =$F20*H20 -> 0 | Z20: =$F20*I20 -> 0 | AA20: =$F20*J20 -> 0.065268817 | AB20: =$F20*K20 -> 0.065268817 | AC20: =$F20*L20 -> 0.065268817 | AD20: =$F20*M20 -> 0.065268817 | AE20: =$F20*N20 -> 0.065268817 | ... AN20: =$F20*W20 -> 0
A21: I | B21: 6 | C21: 5 | D21: I_06_5 | E21: 0.16344086 | F21: =E21-$E$121 -> 0.65268817 | J21: 0.1 | K21: 0.1 | L21: 0.1 | M21: 0.1 | N21: 0.1 | O21: 0.1 | P21: 0.1 | Q21: 0.1 | R21: 0.1 | S21: 0.1 | X21: =$F21*G21 -> 0 | Y21: =$F21*H21 -> 0 | Z21: =$F21*I21 -> 0 | AA21: =$F21*J21 -> 0.065268817 | AB21: =$F21*K21 -> 0.065268817 | AC21: =$F21*L21 -> 0.065268817 | AD21: =$F21*M21 -> 0.065268817 | AE21: =$F21*N21 -> 0.065268817 | ... AN21: =$F21*W21 -> 0
A22: I | B22: 6 | C22: 2 | D22: I_06_2 | E22: 0.098924731 | F22: =E22-$E$121 -> 0.58817204 | J22: 0.1 | K22: 0.1 | L22: 0.1 | M22: 0.1 | N22: 0.1 | O22: 0.1 | P22: 0.1 | Q22: 0.1 | R22: 0.1 | S22: 0.1 | X22: =$F22*G22 -> 0 | Y22: =$F22*H22 -> 0 | Z22: =$F22*I22 -> 0 | AA22: =$F22*J22 -> 0.058817204 | AB22: =$F22*K22 -> 0.058817204 | AC22: =$F22*L22 -> 0.058817204 | AD22: =$F22*M22 -> 0.058817204 | AE22: =$F22*N22 -> 0.058817204 | ... AN22: =$F22*W22 -> 0
A23: I | B23: 6 | C23: 3 | D23: I_06_3 | E23: 0.098924731 | F23: =E23-$E$121 -> 0.58817204 | J23: 0.1 | K23: 0.1 | L23: 0.1 | M23: 0.1 | N23: 0.1 | O23: 0.1 | P23: 0.1 | Q23: 0.1 | R23: 0.1 | S23: 0.1 | X23: =$F23*G23 -> 0 | Y23: =$F23*H23 -> 0 | Z23: =$F23*I23 -> 0 | AA23: =$F23*J23 -> 0.058817204 | AB23: =$F23*K23 -> 0.058817204 | AC23: =$F23*L23 -> 0.058817204 | AD23: =$F23*M23 -> 0.058817204 | AE23: =$F23*N23 -> 0.058817204 | ... AN23: =$F23*W23 -> 0
A24: I | B24: 6 | C24: 1 | D24: I_06_1 | E24: 0.075268817 | F24: =E24-$E$121 -> 0.56451613 | J24: 0.1 | K24: 0.1 | L24: 0.1 | M24: 0.1 | N24: 0.1 | O24: 0.1 | P24: 0.1 | Q24: 0.1 | R24: 0.1 | S24: 0.1 | X24: =$F24*G24 -> 0 | Y24: =$F24*H24 -> 0 | Z24: =$F24*I24 -> 0 | AA24: =$F24*J24 -> 0.056451613 | AB24: =$F24*K24 -> 0.056451613 | AC24: =$F24*L24 -> 0.056451613 | AD24: =$F24*M24 -> 0.056451613 | AE24: =$F24*N24 -> 0.056451613 | ... AN24: =$F24*W24 -> 0
A25: N | B25: 7 | C25: 5 | D25: N_07_5 | E25: -0.37419355 | F25: =E25-$E$121 -> 0.11505376 | R25: 1 | X25: =$F25*G25 -> 0 | Y25: =$F25*H25 -> 0 | Z25: =$F25*I25 -> 0 | AA25: =$F25*J25 -> 0 | AB25: =$F25*K25 -> 0 | AC25: =$F25*L25 -> 0 | AD25: =$F25*M25 -> 0 | AE25: =$F25*N25 -> 0 | ... AN25: =$F25*W25 -> 0
A26: N | B26: 7 | C26: 4 | D26: N_07_4 | E26: -0.46774194 | F26: =E26-$E$121 -> 0.021505376 | R26: 1 | X26: =$F26*G26 -> 0 | Y26: =$F26*H26 -> 0 | Z26: =$F26*I26 -> 0 | AA26: =$F26*J26 -> 0 | AB26: =$F26*K26 -> 0 | AC26: =$F26*L26 -> 0 | AD26: =$F26*M26 -> 0 | AE26: =$F26*N26 -> 0 | ... AN26: =$F26*W26 -> 0
A27: N | B27: 8 | C27: 4 | D27: N_08_4 | E27: -0.46236559 | F27: =E27-$E$121 -> 0.02688172 | R27: 1 | X27: =$F27*G27 -> 0 | Y27: =$F27*H27 -> 0 | Z27: =$F27*I27 -> 0 | AA27: =$F27*J27 -> 0 | AB27: =$F27*K27 -> 0 | AC27: =$F27*L27 -> 0 | AD27: =$F27*M27 -> 0 | AE27: =$F27*N27 -> 0 | ... AN27: =$F27*W27 -> 0
A28: N | B28: 8 | C28: 5 | D28: N_08_5 | E28: -0.47956989 | F28: =E28-$E$121 -> 0.0096774194 | R28: 1 | X28: =$F28*G28 -> 0 | Y28: =$F28*H28 -> 0 | Z28: =$F28*I28 -> 0 | AA28: =$F28*J28 -> 0 | AB28: =$F28*K28 -> 0 | AC28: =$F28*L28 -> 0 | AD28: =$F28*M28 -> 0 | AE28: =$F28*N28 -> 0 | ... AN28: =$F28*W28 -> 0
A29: I | B29: 9 | C29: 5 | D29: I_09_5 | E29: 0.29784946 | F29: =E29-$E$121 -> 0.78709677 | G29: 0.25 | H29: 0.25 | K29: 0.25 | L29: 0.25 | X29: =$F29*G29 -> 0.19677419 | Y29: =$F29*H29 -> 0.19677419 | Z29: =$F29*I29 -> 0 | AA29: =$F29*J29 -> 0 | AB29: =$F29*K29 -> 0.19677419 | AC29: =$F29*L29 -> 0.19677419 | AD29: =$F29*M29 -> 0 | AE29: =$F29*N29 -> 0 | ... AN29: =$F29*W29 -> 0
A30: I | B30: 9 | C30: 4 | D30: I_09_4 | E30: 0.26451613 | F30: =E30-$E$121 -> 0.75376344 | G30: 0.25 | H30: 0.25 | K30: 0.25 | L30: 0.25 | X30: =$F30*G30 -> 0.18844086 | Y30: =$F30*H30 -> 0.18844086 | Z30: =$F30*I30 -> 0 | AA30: =$F30*J30 -> 0 | AB30: =$F30*K30 -> 0.18844086 | AC30: =$F30*L30 -> 0.18844086 | AD30: =$F30*M30 -> 0 | AE30: =$F30*N30 -> 0 | ... AN30: =$F30*W30 -> 0
A31: I | B31: 9 | C31: 3 | D31: I_09_3 | E31: 0.21935484 | F31: =E31-$E$121 -> 0.70860215 | G31: 0.25 | H31: 0.25 | K31: 0.25 | L31: 0.25 | X31: =$F31*G31 -> 0.17715054 | Y31: =$F31*H31 -> 0.17715054 | Z31: =$F31*I31 -> 0 | AA31: =$F31*J31 -> 0 | AB31: =$F31*K31 -> 0.17715054 | AC31: =$F31*L31 -> 0.17715054 | AD31: =$F31*M31 -> 0 | AE31: =$F31*N31 -> 0 | ... AN31: =$F31*W31 -> 0
A32: I | B32: 9 | C32: 1 | D32: I_09_1 | E32: 0.20860215 | F32: =E32-$E$121 -> 0.69784946 | G32: 0.25 | H32: 0.25 | K32: 0.25 | L32: 0.25 | X32: =$F32*G32 -> 0.17446237 | Y32: =$F32*H32 -> 0.17446237 | Z32: =$F32*I32 -> 0 | AA32: =$F32*J32 -> 0 | AB32: =$F32*K32 -> 0.17446237 | AC32: =$F32*L32 -> 0.17446237 | AD32: =$F32*M32 -> 0 | AE32: =$F32*N32 -> 0 | ... AN32: =$F32*W32 -> 0
A33: I | B33: 9 | C33: 2 | D33: I_09_2 | E33: 0.20860215 | F33: =E33-$E$121 -> 0.69784946 | G33: 0.25 | H33: 0.25 | K33: 0.25 | L33: 0.25 | X33: =$F33*G33 -> 0.17446237 | Y33: =$F33*H33 -> 0.17446237 | Z33: =$F33*I33 -> 0 | AA33: =$F33*J33 -> 0 | AB33: =$F33*K33 -> 0.17446237 | AC33: =$F33*L33 -> 0.17446237 | AD33: =$F33*M33 -> 0 | AE33: =$F33*N33 -> 0 | ... AN33: =$F33*W33 -> 0
A34: I | B34: 10 | C34: 5 | D34: I_10_5 | E34: 0.29784946 | F34: =E34-$E$121 -> 0.78709677 | G34: 0.2 | H34: 0.2 | I34: 0.2 | K34: 0.2 | L34: 0.2 | X34: =$F34*G34 -> 0.15741935 | Y34: =$F34*H34 -> 0.15741935 | Z34: =$F34*I34 -> 0.15741935 | AA34: =$F34*J34 -> 0 | AB34: =$F34*K34 -> 0.15741935 | AC34: =$F34*L34 -> 0.15741935 | AD34: =$F34*M34 -> 0 | AE34: =$F34*N34 -> 0 | ... AN34: =$F34*W34 -> 0
A35: I | B35: 10 | C35: 4 | D35: I_10_4 | E35: 0.26451613 | F35: =E35-$E$121 -> 0.75376344 | G35: 0.2 | H35: 0.2 | I35: 0.2 | K35: 0.2 | L35: 0.2 | X35: =$F35*G35 -> 0.15075269 | Y35: =$F35*H35 -> 0.15075269 | Z35: =$F35*I35 -> 0.15075269 | AA35: =$F35*J35 -> 0 | AB35: =$F35*K35 -> 0.15075269 | AC35: =$F35*L35 -> 0.15075269 | AD35: =$F35*M35 -> 0 | AE35: =$F35*N35 -> 0 | ... AN35: =$F35*W35 -> 0
A36: I | B36: 10 | C36: 3 | D36: I_10_3 | E36: 0.21935484 | F36: =E36-$E$121 -> 0.70860215 | G36: 0.2 | H36: 0.2 | I36: 0.2 | K36: 0.2 | L36: 0.2 | X36: =$F36*G36 -> 0.14172043 | Y36: =$F36*H36 -> 0.14172043 | Z36: =$F36*I36 -> 0.14172043 | AA36: =$F36*J36 -> 0 | AB36: =$F36*K36 -> 0.14172043 | AC36: =$F36*L36 -> 0.14172043 | AD36: =$F36*M36 -> 0 | AE36: =$F36*N36 -> 0 | ... AN36: =$F36*W36 -> 0
A37: I | B37: 10 | C37: 1 | D37: I_10_1 | E37: 0.20860215 | F37: =E37-$E$121 -> 0.69784946 | G37: 0.2 | H37: 0.2 | I37: 0.2 | K37: 0.2 | L37: 0.2 | X37: =$F37*G37 -> 0.13956989 | Y37: =$F37*H37 -> 0.13956989 | Z37: =$F37*I37 -> 0.13956989 | AA37: =$F37*J37 -> 0 | AB37: =$F37*K37 -> 0.13956989 | AC37: =$F37*L37 -> 0.13956989 | AD37: =$F37*M37 -> 0 | AE37: =$F37*N37 -> 0 | ... AN37: =$F37*W37 -> 0
A38: I | B38: 10 | C38: 2 | D38: I_10_2 | E38: 0.20860215 | F38: =E38-$E$121 -> 0.69784946 | G38: 0.2 | H38: 0.2 | I38: 0.2 | K38: 0.2 | L38: 0.2 | X38: =$F38*G38 -> 0.13956989 | Y38: =$F38*H38 -> 0.13956989 | Z38: =$F38*I38 -> 0.13956989 | AA38: =$F38*J38 -> 0 | AB38: =$F38*K38 -> 0.13956989 | AC38: =$F38*L38 -> 0.13956989 | AD38: =$F38*M38 -> 0 | AE38: =$F38*N38 -> 0 | ... AN38: =$F38*W38 -> 0
A39: I | B39: 11 | C39: 3 | D39: I_11_3 | E39: 0.34086022 | F39: =E39-$E$121 -> 0.83010753 | H39: 1 | X39: =$F39*G39 -> 0 | Y39: =$F39*H39 -> 0.83010753 | Z39: =$F39*I39 -> 0 | AA39: =$F39*J39 -> 0 | AB39: =$F39*K39 -> 0 | AC39: =$F39*L39 -> 0 | AD39: =$F39*M39 -> 0 | AE39: =$F39*N39 -> 0 | ... AN39: =$F39*W39 -> 0
A40: I | B40: 11 | C40: 5 | D40: I_11_5 | E40: 0.29784946 | F40: =E40-$E$121 -> 0.78709677 | H40: 1 | X40: =$F40*G40 -> 0 | Y40: =$F40*H40 -> 0.78709677 | Z40: =$F40*I40 -> 0 | AA40: =$F40*J40 -> 0 | AB40: =$F40*K40 -> 0 | AC40: =$F40*L40 -> 0 | AD40: =$F40*M40 -> 0 | AE40: =$F40*N40 -> 0 | ... AN40: =$F40*W40 -> 0
A41: I | B41: 11 | C41: 4 | D41: I_11_4 | E41: 0.26451613 | F41: =E41-$E$121 -> 0.75376344 | H41: 1 | X41: =$F41*G41 -> 0 | Y41: =$F41*H41 -> 0.75376344 | Z41: =$F41*I41 -> 0 | AA41: =$F41*J41 -> 0 | AB41: =$F41*K41 -> 0 | AC41: =$F41*L41 -> 0 | AD41: =$F41*M41 -> 0 | AE41: =$F41*N41 -> 0 | ... AN41: =$F41*W41 -> 0
A42: I | B42: 11 | C42: 1 | D42: I_11_1 | E42: 0.20860215 | F42: =E42-$E$121 -> 0.69784946 | H42: 1 | X42: =$F42*G42 -> 0 | Y42: =$F42*H42 -> 0.69784946 | Z42: =$F42*I42 -> 0 | AA42: =$F42*J42 -> 0 | AB42: =$F42*K42 -> 0 | AC42: =$F42*L42 -> 0 | AD42: =$F42*M42 -> 0 | AE42: =$F42*N42 -> 0 | ... AN42: =$F42*W42 -> 0
A43: I | B43: 11 | C43: 2 | D43: I_11_2 | E43: 0.20860215 | F43: =E43-$E$121 -> 0.69784946 | H43: 1 | X43: =$F43*G43 -> 0 | Y43: =$F43*H43 -> 0.69784946 | Z43: =$F43*I43 -> 0 | AA43: =$F43*J43 -> 0 | AB43: =$F43*K43 -> 0 | AC43: =$F43*L43 -> 0 | AD43: =$F43*M43 -> 0 | AE43: =$F43*N43 -> 0 | ... AN43: =$F43*W43 -> 0
A44: I | B44: 12 | C44: 4 | D44: I_12_4 | E44: 0.093548387 | F44: =E44-$E$121 -> 0.5827957 | G44: 1 | X44: =$F44*G44 -> 0.5827957 | Y44: =$F44*H44 -> 0 | Z44: =$F44*I44 -> 0 | AA44: =$F44*J44 -> 0 | AB44: =$F44*K44 -> 0 | AC44: =$F44*L44 -> 0 | AD44: =$F44*M44 -> 0 | AE44: =$F44*N44 -> 0 | ... AN44: =$F44*W44 -> 0
A45: I | B45: 12 | C45: 3 | D45: I_12_3 | E45: 0.048387097 | F45: =E45-$E$121 -> 0.53763441 | G45: 1 | X45: =$F45*G45 -> 0.53763441 | Y45: =$F45*H45 -> 0 | Z45: =$F45*I45 -> 0 | AA45: =$F45*J45 -> 0 | AB45: =$F45*K45 -> 0 | AC45: =$F45*L45 -> 0 | AD45: =$F45*M45 -> 0 | AE45: =$F45*N45 -> 0 | ... AN45: =$F45*W45 -> 0
A46: I | B46: 12 | C46: 1 | D46: I_12_1 | E46: 0.037634409 | F46: =E46-$E$121 -> 0.52688172 | G46: 1 | X46: =$F46*G46 -> 0.52688172 | Y46: =$F46*H46 -> 0 | Z46: =$F46*I46 -> 0 | AA46: =$F46*J46 -> 0 | AB46: =$F46*K46 -> 0 | AC46: =$F46*L46 -> 0 | AD46: =$F46*M46 -> 0 | AE46: =$F46*N46 -> 0 | ... AN46: =$F46*W46 -> 0
A47: I | B47: 12 | C47: 2 | D47: I_12_2 | E47: 0.037634409 | F47: =E47-$E$121 -> 0.52688172 | G47: 1 | X47: =$F47*G47 -> 0.52688172 | Y47: =$F47*H47 -> 0 | Z47: =$F47*I47 -> 0 | AA47: =$F47*J47 -> 0 | AB47: =$F47*K47 -> 0 | AC47: =$F47*L47 -> 0 | AD47: =$F47*M47 -> 0 | AE47: =$F47*N47 -> 0 | ... AN47: =$F47*W47 -> 0
A48: I | B48: 12 | C48: 5 | D48: I_12_5 | E48: 0.031182796 | F48: =E48-$E$121 -> 0.52043011 | G48: 1 | X48: =$F48*G48 -> 0.52043011 | Y48: =$F48*H48 -> 0 | Z48: =$F48*I48 -> 0 | AA48: =$F48*J48 -> 0 | AB48: =$F48*K48 -> 0 | AC48: =$F48*L48 -> 0 | AD48: =$F48*M48 -> 0 | AE48: =$F48*N48 -> 0 | ... AN48: =$F48*W48 -> 0
A49: I | B49: 13 | C49: 5 | D49: I_13_5 | E49: -0.048387097 | F49: =E49-$E$121 -> 0.44086022 | G49: 0.2 | H49: 0.2 | I49: 0.2 | K49: 0.2 | L49: 0.2 | X49: =$F49*G49 -> 0.088172043 | Y49: =$F49*H49 -> 0.088172043 | Z49: =$F49*I49 -> 0.088172043 | AA49: =$F49*J49 -> 0 | AB49: =$F49*K49 -> 0.088172043 | AC49: =$F49*L49 -> 0.088172043 | AD49: =$F49*M49 -> 0 | AE49: =$F49*N49 -> 0 | ... AN49: =$F49*W49 -> 0
A50: I | B50: 13 | C50: 4 | D50: I_13_4 | E50: -0.11827957 | F50: =E50-$E$121 -> 0.37096774 | G50: 0.2 | H50: 0.2 | I50: 0.2 | K50: 0.2 | L50: 0.2 | X50: =$F50*G50 -> 0.074193548 | Y50: =$F50*H50 -> 0.074193548 | Z50: =$F50*I50 -> 0.074193548 | AA50: =$F50*J50 -> 0 | AB50: =$F50*K50 -> 0.074193548 | AC50: =$F50*L50 -> 0.074193548 | AD50: =$F50*M50 -> 0 | AE50: =$F50*N50 -> 0 | ... AN50: =$F50*W50 -> 0
A51: I | B51: 13 | C51: 3 | D51: I_13_3 | E51: -0.20860215 | F51: =E51-$E$121 -> 0.28064516 | G51: 0.2 | H51: 0.2 | I51: 0.2 | K51: 0.2 | L51: 0.2 | X51: =$F51*G51 -> 0.056129032 | Y51: =$F51*H51 -> 0.056129032 | Z51: =$F51*I51 -> 0.056129032 | AA51: =$F51*J51 -> 0 | AB51: =$F51*K51 -> 0.056129032 | AC51: =$F51*L51 -> 0.056129032 | AD51: =$F51*M51 -> 0 | AE51: =$F51*N51 -> 0 | ... AN51: =$F51*W51 -> 0
A52: I | B52: 14 | C52: 5 | D52: I_14_5 | E52: -0.016129032 | F52: =E52-$E$121 -> 0.47311828 | J52: 0.1 | K52: 0.1 | L52: 0.1 | M52: 0.1 | N52: 0.1 | O52: 0.1 | P52: 0.1 | Q52: 0.1 | R52: 0.1 | S52: 0.1 | X52: =$F52*G52 -> 0 | Y52: =$F52*H52 -> 0 | Z52: =$F52*I52 -> 0 | AA52: =$F52*J52 -> 0.047311828 | AB52: =$F52*K52 -> 0.047311828 | AC52: =$F52*L52 -> 0.047311828 | AD52: =$F52*M52 -> 0.047311828 | AE52: =$F52*N52 -> 0.047311828 | ... AN52: =$F52*W52 -> 0
A53: I | B53: 14 | C53: 4 | D53: I_14_4 | E53: -0.10645161 | F53: =E53-$E$121 -> 0.3827957 | J53: 0.1 | K53: 0.1 | L53: 0.1 | M53: 0.1 | N53: 0.1 | O53: 0.1 | P53: 0.1 | Q53: 0.1 | R53: 0.1 | S53: 0.1 | X53: =$F53*G53 -> 0 | Y53: =$F53*H53 -> 0 | Z53: =$F53*I53 -> 0 | AA53: =$F53*J53 -> 0.03827957 | AB53: =$F53*K53 -> 0.03827957 | AC53: =$F53*L53 -> 0.03827957 | AD53: =$F53*M53 -> 0.03827957 | AE53: =$F53*N53 -> 0.03827957 | ... AN53: =$F53*W53 -> 0
A54: I | B54: 14 | C54: 3 | D54: I_14_3 | E54: -0.11182796 | F54: =E54-$E$121 -> 0.37741935 | J54: 0.1 | K54: 0.1 | L54: 0.1 | M54: 0.1 | N54: 0.1 | O54: 0.1 | P54: 0.1 | Q54: 0.1 | R54: 0.1 | S54: 0.1 | X54: =$F54*G54 -> 0 | Y54: =$F54*H54 -> 0 | Z54: =$F54*I54 -> 0 | AA54: =$F54*J54 -> 0.037741935 | AB54: =$F54*K54 -> 0.037741935 | AC54: =$F54*L54 -> 0.037741935 | AD54: =$F54*M54 -> 0.037741935 | AE54: =$F54*N54 -> 0.037741935 | ... AN54: =$F54*W54 -> 0
A55: I | B55: 15 | C55: 4 | D55: I_15_4 | E55: 0.093548387 | F55: =E55-$E$121 -> 0.5827957 | K55: 0.5 | L55: 0.5 | X55: =$F55*G55 -> 0 | Y55: =$F55*H55 -> 0 | Z55: =$F55*I55 -> 0 | AA55: =$F55*J55 -> 0 | AB55: =$F55*K55 -> 0.29139785 | AC55: =$F55*L55 -> 0.29139785 | AD55: =$F55*M55 -> 0 | AE55: =$F55*N55 -> 0 | ... AN55: =$F55*W55 -> 0
A56: I | B56: 15 | C56: 3 | D56: I_15_3 | E56: 0.048387097 | F56: =E56-$E$121 -> 0.53763441 | K56: 0.5 | L56: 0.5 | X56: =$F56*G56 -> 0 | Y56: =$F56*H56 -> 0 | Z56: =$F56*I56 -> 0 | AA56: =$F56*J56 -> 0 | AB56: =$F56*K56 -> 0.2688172 | AC56: =$F56*L56 -> 0.2688172 | AD56: =$F56*M56 -> 0 | AE56: =$F56*N56 -> 0 | ... AN56: =$F56*W56 -> 0
A57: I | B57: 15 | C57: 1 | D57: I_15_1 | E57: 0.037634409 | F57: =E57-$E$121 -> 0.52688172 | K57: 0.5 | L57: 0.5 | X57: =$F57*G57 -> 0 | Y57: =$F57*H57 -> 0 | Z57: =$F57*I57 -> 0 | AA57: =$F57*J57 -> 0 | AB57: =$F57*K57 -> 0.26344086 | AC57: =$F57*L57 -> 0.26344086 | AD57: =$F57*M57 -> 0 | AE57: =$F57*N57 -> 0 | ... AN57: =$F57*W57 -> 0
A58: I | B58: 15 | C58: 2 | D58: I_15_2 | E58: 0.037634409 | F58: =E58-$E$121 -> 0.52688172 | K58: 0.5 | L58: 0.5 | X58: =$F58*G58 -> 0 | Y58: =$F58*H58 -> 0 | Z58: =$F58*I58 -> 0 | AA58: =$F58*J58 -> 0 | AB58: =$F58*K58 -> 0.26344086 | AC58: =$F58*L58 -> 0.26344086 | AD58: =$F58*M58 -> 0 | AE58: =$F58*N58 -> 0 | ... AN58: =$F58*W58 -> 0
A59: I | B59: 15 | C59: 5 | D59: I_15_5 | E59: 0.031182796 | F59: =E59-$E$121 -> 0.52043011 | K59: 0.5 | L59: 0.5 | X59: =$F59*G59 -> 0 | Y59: =$F59*H59 -> 0 | Z59: =$F59*I59 -> 0 | AA59: =$F59*J59 -> 0 | AB59: =$F59*K59 -> 0.26021505 | AC59: =$F59*L59 -> 0.26021505 | AD59: =$F59*M59 -> 0 | AE59: =$F59*N59 -> 0 | ... AN59: =$F59*W59 -> 0
A60: I | B60: 16 | C60: 3 | D60: I_16_3 | E60: 0.34086022 | F60: =E60-$E$121 -> 0.83010753 | O60: 0.5 | S60: 0.5 | X60: =$F60*G60 -> 0 | Y60: =$F60*H60 -> 0 | Z60: =$F60*I60 -> 0 | AA60: =$F60*J60 -> 0 | AB60: =$F60*K60 -> 0 | AC60: =$F60*L60 -> 0 | AD60: =$F60*M60 -> 0 | AE60: =$F60*N60 -> 0 | ... AN60: =$F60*W60 -> 0
A61: I | B61: 16 | C61: 2 | D61: I_16_2 | E61: 0.31182796 | F61: =E61-$E$121 -> 0.80107527 | O61: 0.5 | S61: 0.5 | X61: =$F61*G61 -> 0 | Y61: =$F61*H61 -> 0 | Z61: =$F61*I61 -> 0 | AA61: =$F61*J61 -> 0 | AB61: =$F61*K61 -> 0 | AC61: =$F61*L61 -> 0 | AD61: =$F61*M61 -> 0 | AE61: =$F61*N61 -> 0 | ... AN61: =$F61*W61 -> 0
A62: I | B62: 16 | C62: 5 | D62: I_16_5 | E62: 0.29784946 | F62: =E62-$E$121 -> 0.78709677 | O62: 0.5 | S62: 0.5 | X62: =$F62*G62 -> 0 | Y62: =$F62*H62 -> 0 | Z62: =$F62*I62 -> 0 | AA62: =$F62*J62 -> 0 | AB62: =$F62*K62 -> 0 | AC62: =$F62*L62 -> 0 | AD62: =$F62*M62 -> 0 | AE62: =$F62*N62 -> 0 | ... AN62: =$F62*W62 -> 0
A63: I | B63: 16 | C63: 4 | D63: I_16_4 | E63: 0.26451613 | F63: =E63-$E$121 -> 0.75376344 | O63: 0.5 | S63: 0.5 | X63: =$F63*G63 -> 0 | Y63: =$F63*H63 -> 0 | Z63: =$F63*I63 -> 0 | AA63: =$F63*J63 -> 0 | AB63: =$F63*K63 -> 0 | AC63: =$F63*L63 -> 0 | AD63: =$F63*M63 -> 0 | AE63: =$F63*N63 -> 0 | ... AN63: =$F63*W63 -> 0
A64: I | B64: 16 | C64: 1 | D64: I_16_1 | E64: 0.20860215 | F64: =E64-$E$121 -> 0.69784946 | O64: 0.5 | S64: 0.5 | X64: =$F64*G64 -> 0 | Y64: =$F64*H64 -> 0 | Z64: =$F64*I64 -> 0 | AA64: =$F64*J64 -> 0 | AB64: =$F64*K64 -> 0 | AC64: =$F64*L64 -> 0 | AD64: =$F64*M64 -> 0 | AE64: =$F64*N64 -> 0 | ... AN64: =$F64*W64 -> 0
A65: I | B65: 17 | C65: 4 | D65: I_17_4 | E65: 0.012903226 | F65: =E65-$E$121 -> 0.50215054 | O65: 0.5 | S65: 0.5 | X65: =$F65*G65 -> 0 | Y65: =$F65*H65 -> 0 | Z65: =$F65*I65 -> 0 | AA65: =$F65*J65 -> 0 | AB65: =$F65*K65 -> 0 | AC65: =$F65*L65 -> 0 | AD65: =$F65*M65 -> 0 | AE65: =$F65*N65 -> 0 | ... AN65: =$F65*W65 -> 0
A66: I | B66: 17 | C66: 2 | D66: I_17_2 | E66: -0.0064516129 | F66: =E66-$E$121 -> 0.4827957 | O66: 0.5 | S66: 0.5 | X66: =$F66*G66 -> 0 | Y66: =$F66*H66 -> 0 | Z66: =$F66*I66 -> 0 | AA66: =$F66*J66 -> 0 | AB66: =$F66*K66 -> 0 | AC66: =$F66*L66 -> 0 | AD66: =$F66*M66 -> 0 | AE66: =$F66*N66 -> 0 | ... AN66: =$F66*W66 -> 0
A67: I | B67: 17 | C67: 1 | D67: I_17_1 | E67: -0.035483871 | F67: =E67-$E$121 -> 0.45376344 | O67: 0.5 | S67: 0.5 | X67: =$F67*G67 -> 0 | Y67: =$F67*H67 -> 0 | Z67: =$F67*I67 -> 0 | AA67: =$F67*J67 -> 0 | AB67: =$F67*K67 -> 0 | AC67: =$F67*L67 -> 0 | AD67: =$F67*M67 -> 0 | AE67: =$F67*N67 -> 0 | ... AN67: =$F67*W67 -> 0
A68: I | B68: 17 | C68: 5 | D68: I_17_5 | E68: -0.049462366 | F68: =E68-$E$121 -> 0.43978495 | O68: 0.5 | S68: 0.5 | X68: =$F68*G68 -> 0 | Y68: =$F68*H68 -> 0 | Z68: =$F68*I68 -> 0 | AA68: =$F68*J68 -> 0 | AB68: =$F68*K68 -> 0 | AC68: =$F68*L68 -> 0 | AD68: =$F68*M68 -> 0 | AE68: =$F68*N68 -> 0 | ... AN68: =$F68*W68 -> 0
A69: I | B69: 17 | C69: 3 | D69: I_17_3 | E69: -0.082795699 | F69: =E69-$E$121 -> 0.40645161 | O69: 0.5 | S69: 0.5 | X69: =$F69*G69 -> 0 | Y69: =$F69*H69 -> 0 | Z69: =$F69*I69 -> 0 | AA69: =$F69*J69 -> 0 | AB69: =$F69*K69 -> 0 | AC69: =$F69*L69 -> 0 | AD69: =$F69*M69 -> 0 | AE69: =$F69*N69 -> 0 | ... AN69: =$F69*W69 -> 0
A70: I | B70: 18 | C70: 3 | D70: I_18_3 | E70: -0.0064516129 | F70: =E70-$E$121 -> 0.4827957 | O70: 0.5 | S70: 0.5 | X70: =$F70*G70 -> 0 | Y70: =$F70*H70 -> 0 | Z70: =$F70*I70 -> 0 | AA70: =$F70*J70 -> 0 | AB70: =$F70*K70 -> 0 | AC70: =$F70*L70 -> 0 | AD70: =$F70*M70 -> 0 | AE70: =$F70*N70 -> 0 | ... AN70: =$F70*W70 -> 0
A71: I | B71: 18 | C71: 2 | D71: I_18_2 | E71: -0.035483871 | F71: =E71-$E$121 -> 0.45376344 | O71: 0.5 | S71: 0.5 | X71: =$F71*G71 -> 0 | Y71: =$F71*H71 -> 0 | Z71: =$F71*I71 -> 0 | AA71: =$F71*J71 -> 0 | AB71: =$F71*K71 -> 0 | AC71: =$F71*L71 -> 0 | AD71: =$F71*M71 -> 0 | AE71: =$F71*N71 -> 0 | ... AN71: =$F71*W71 -> 0
... A84: I | B84: 20 | C84: 2 | D84: I_20_2 | E84: 0.047311828 | F84: =E84-$E$121 -> 0.53655914 | O84: 0.5 | S84: 0.5 | X84: =$F84*G84 -> 0 | Y84: =$F84*H84 -> 0 | Z84: =$F84*I84 -> 0 | AA84: =$F84*J84 -> 0 | AB84: =$F84*K84 -> 0 | AC84: =$F84*L84 -> 0 | AD84: =$F84*M84 -> 0 | AE84: =$F84*N84 -> 0 | ... AN84: =$F84*W84 -> 0
A85: N | B85: 21 | C85: 4 | D85: N_21_4 | E85: -0.32580645 | F85: =E85-$E$121 -> 0.16344086 | S85: 1 | X85: =$F85*G85 -> 0 | Y85: =$F85*H85 -> 0 | Z85: =$F85*I85 -> 0 | AA85: =$F85*J85 -> 0 | AB85: =$F85*K85 -> 0 | AC85: =$F85*L85 -> 0 | AD85: =$F85*M85 -> 0 | AE85: =$F85*N85 -> 0 | ... AN85: =$F85*W85 -> 0
A86: N | B86: 21 | C86: 5 | D86: N_21_5 | E86: -0.3688172 | F86: =E86-$E$121 -> 0.12043011 | S86: 1 | X86: =$F86*G86 -> 0 | Y86: =$F86*H86 -> 0 | Z86: =$F86*I86 -> 0 | AA86: =$F86*J86 -> 0 | AB86: =$F86*K86 -> 0 | AC86: =$F86*L86 -> 0 | AD86: =$F86*M86 -> 0 | AE86: =$F86*N86 -> 0 | ... AN86: =$F86*W86 -> 0
A87: I | B87: 22 | C87: 4 | D87: I_22_4 | E87: -0.25376344 | F87: =E87-$E$121 -> 0.23548387 | J87: 0.5 | L87: 0.5 | X87: =$F87*G87 -> 0 | Y87: =$F87*H87 -> 0 | Z87: =$F87*I87 -> 0 | AA87: =$F87*J87 -> 0.11774194 | AB87: =$F87*K87 -> 0 | AC87: =$F87*L87 -> 0.11774194 | AD87: =$F87*M87 -> 0 | AE87: =$F87*N87 -> 0 | ... AN87: =$F87*W87 -> 0
A88: I | B88: 22 | C88: 3 | D88: I_22_3 | E88: -0.29892473 | F88: =E88-$E$121 -> 0.19032258 | J88: 0.5 | L88: 0.5 | X88: =$F88*G88 -> 0 | Y88: =$F88*H88 -> 0 | Z88: =$F88*I88 -> 0 | AA88: =$F88*J88 -> 0.09516129 | AB88: =$F88*K88 -> 0 | AC88: =$F88*L88 -> 0.09516129 | AD88: =$F88*M88 -> 0 | AE88: =$F88*N88 -> 0 | ... AN88: =$F88*W88 -> 0
A89: I | B89: 22 | C89: 1 | D89: I_22_1 | E89: -0.30967742 | F89: =E89-$E$121 -> 0.17956989 | J89: 0.5 | L89: 0.5 | X89: =$F89*G89 -> 0 | Y89: =$F89*H89 -> 0 | Z89: =$F89*I89 -> 0 | AA89: =$F89*J89 -> 0.089784946 | AB89: =$F89*K89 -> 0 | AC89: =$F89*L89 -> 0.089784946 | AD89: =$F89*M89 -> 0 | AE89: =$F89*N89 -> 0 | ... AN89: =$F89*W89 -> 0
A90: I | B90: 22 | C90: 2 | D90: I_22_2 | E90: -0.30967742 | F90: =E90-$E$121 -> 0.17956989 | J90: 0.5 | L90: 0.5 | X90: =$F90*G90 -> 0 | Y90: =$F90*H90 -> 0 | Z90: =$F90*I90 -> 0 | AA90: =$F90*J90 -> 0.089784946 | AB90: =$F90*K90 -> 0 | AC90: =$F90*L90 -> 0.089784946 | AD90: =$F90*M90 -> 0 | AE90: =$F90*N90 -> 0 | ... AN90: =$F90*W90 -> 0
A91: I | B91: 22 | C91: 5 | D91: I_22_5 | E91: -0.31612903 | F91: =E91-$E$121 -> 0.17311828 | J91: 0.5 | L91: 0.5 | X91: =$F91*G91 -> 0 | Y91: =$F91*H91 -> 0 | Z91: =$F91*I91 -> 0 | AA91: =$F91*J91 -> 0.08655914 | AB91: =$F91*K91 -> 0 | AC91: =$F91*L91 -> 0.08655914 | AD91: =$F91*M91 -> 0 | AE91: =$F91*N91 -> 0 | ... AN91: =$F91*W91 -> 0
A92: I | B92: 23 | C92: 4 | D92: I_23_4 | E92: -0.067741935 | F92: =E92-$E$121 -> 0.42150538 | J92: 0.5 | L92: 0.5 | X92: =$F92*G92 -> 0 | Y92: =$F92*H92 -> 0 | Z92: =$F92*I92 -> 0 | AA92: =$F92*J92 -> 0.21075269 | AB92: =$F92*K92 -> 0 | AC92: =$F92*L92 -> 0.21075269 | AD92: =$F92*M92 -> 0 | AE92: =$F92*N92 -> 0 | ... AN92: =$F92*W92 -> 0
A93: I | B93: 23 | C93: 3 | D93: I_23_3 | E93: -0.11290323 | F93: =E93-$E$121 -> 0.37634409 | J93: 0.5 | L93: 0.5 | X93: =$F93*G93 -> 0 | Y93: =$F93*H93 -> 0 | Z93: =$F93*I93 -> 0 | AA93: =$F93*J93 -> 0.18817204 | AB93: =$F93*K93 -> 0 | AC93: =$F93*L93 -> 0.18817204 | AD93: =$F93*M93 -> 0 | AE93: =$F93*N93 -> 0 | ... AN93: =$F93*W93 -> 0
A94: I | B94: 23 | C94: 1 | D94: I_23_1 | E94: -0.12365591 | F94: =E94-$E$121 -> 0.3655914 | J94: 0.5 | L94: 0.5 | X94: =$F94*G94 -> 0 | Y94: =$F94*H94 -> 0 | Z94: =$F94*I94 -> 0 | AA94: =$F94*J94 -> 0.1827957 | AB94: =$F94*K94 -> 0 | AC94: =$F94*L94 -> 0.1827957 | AD94: =$F94*M94 -> 0 | AE94: =$F94*N94 -> 0 | ... AN94: =$F94*W94 -> 0
A95: I | B95: 23 | C95: 2 | D95: I_23_2 | E95: -0.12365591 | F95: =E95-$E$121 -> 0.3655914 | J95: 0.5 | L95: 0.5 | X95: =$F95*G95 -> 0 | Y95: =$F95*H95 -> 0 | Z95: =$F95*I95 -> 0 | AA95: =$F95*J95 -> 0.1827957 | AB95: =$F95*K95 -> 0 | AC95: =$F95*L95 -> 0.1827957 | AD95: =$F95*M95 -> 0 | AE95: =$F95*N95 -> 0 | ... AN95: =$F95*W95 -> 0
A96: I | B96: 23 | C96: 5 | D96: I_23_5 | E96: -0.13010753 | F96: =E96-$E$121 -> 0.35913978 | J96: 0.5 | L96: 0.5 | X96: =$F96*G96 -> 0 | Y96: =$F96*H96 -> 0 | Z96: =$F96*I96 -> 0 | AA96: =$F96*J96 -> 0.17956989 | AB96: =$F96*K96 -> 0 | AC96: =$F96*L96 -> 0.17956989 | AD96: =$F96*M96 -> 0 | AE96: =$F96*N96 -> 0 | ... AN96: =$F96*W96 -> 0
A97: I | B97: 24 | C97: 5 | D97: I_24_5 | E97: 0.12688172 | F97: =E97-$E$121 -> 0.61612903 | J97: 0.33 | K97: 0.33 | L97: 0.33 | X97: =$F97*G97 -> 0 | Y97: =$F97*H97 -> 0 | Z97: =$F97*I97 -> 0 | AA97: =$F97*J97 -> 0.20332258 | AB97: =$F97*K97 -> 0.20332258 | AC97: =$F97*L97 -> 0.20332258 | AD97: =$F97*M97 -> 0 | AE97: =$F97*N97 -> 0 | ... AN97: =$F97*W97 -> 0
A98: I | B98: 24 | C98: 3 | D98: I_24_3 | E98: 0.093548387 | F98: =E98-$E$121 -> 0.5827957 | J98: 0.33 | K98: 0.33 | L98: 0.33 | X98: =$F98*G98 -> 0 | Y98: =$F98*H98 -> 0 | Z98: =$F98*I98 -> 0 | AA98: =$F98*J98 -> 0.19232258 | AB98: =$F98*K98 -> 0.19232258 | AC98: =$F98*L98 -> 0.19232258 | AD98: =$F98*M98 -> 0 | AE98: =$F98*N98 -> 0 | ... AN98: =$F98*W98 -> 0
A99: I | B99: 24 | C99: 4 | D99: I_24_4 | E99: 0.093548387 | F99: =E99-$E$121 -> 0.5827957 | J99: 0.33 | K99: 0.33 | L99: 0.33 | X99: =$F99*G99 -> 0 | Y99: =$F99*H99 -> 0 | Z99: =$F99*I99 -> 0 | AA99: =$F99*J99 -> 0.19232258 | AB99: =$F99*K99 -> 0.19232258 | AC99: =$F99*L99 -> 0.19232258 | AD99: =$F99*M99 -> 0 | AE99: =$F99*N99 -> 0 | ... AN99: =$F99*W99 -> 0
A100: I | B100: 24 | C100: 2 | D100: I_24_2 | E100: 0.048387097 | F100: =E100-$E$121 -> 0.53763441 | J100: 0.33 | K100: 0.33 | L100: 0.33 | X100: =$F100*G100 -> 0 | Y100: =$F100*H100 -> 0 | Z100: =$F100*I100 -> 0 | AA100: =$F100*J100 -> 0.17741935 | AB100: =$F100*K100 -> 0.17741935 | AC100: =$F100*L100 -> 0.17741935 | AD100: =$F100*M100 -> 0 | AE100: =$F100*N100 -> 0 | ... AN100: =$F100*W100 -> 0
A101: I | B101: 24 | C101: 1 | D101: I_24_1 | E101: 0.037634409 | F101: =E101-$E$121 -> 0.52688172 | J101: 0.33 | K101: 0.33 | L101: 0.33 | X101: =$F101*G101 -> 0 | Y101: =$F101*H101 -> 0 | Z101: =$F101*I101 -> 0 | AA101: =$F101*J101 -> 0.17387097 | AB101: =$F101*K101 -> 0.17387097 | AC101: =$F101*L101 -> 0.17387097 | AD101: =$F101*M101 -> 0 | AE101: =$F101*N101 -> 0 | ... AN101: =$F101*W101 -> 0
A102: I | B102: 25 | C102: 4 | D102: I_25_4 | E102: -0.082795699 | F102: =E102-$E$121 -> 0.40645161 | M102: 0.33 | N102: 0.33 | P102: 0.33 | X102: =$F102*G102 -> 0 | Y102: =$F102*H102 -> 0 | Z102: =$F102*I102 -> 0 | AA102: =$F102*J102 -> 0 | AB102: =$F102*K102 -> 0 | AC102: =$F102*L102 -> 0 | AD102: =$F102*M102 -> 0.13412903 | AE102: =$F102*N102 -> 0.13412903 | ... AN102: =$F102*W102 -> 0
A103: I | B103: 25 | C103: 3 | D103: I_25_3 | E103: -0.12795699 | F103: =E103-$E$121 -> 0.36129032 | M103: 0.33 | N103: 0.33 | P103: 0.33 | X103: =$F103*G103 -> 0 | Y103: =$F103*H103 -> 0 | Z103: =$F103*I103 -> 0 | AA103: =$F103*J103 -> 0 | AB103: =$F103*K103 -> 0 | AC103: =$F103*L103 -> 0 | AD103: =$F103*M103 -> 0.11922581 | AE103: =$F103*N103 -> 0.11922581 | ... AN103: =$F103*W103 -> 0
A104: I | B104: 25 | C104: 1 | D104: I_25_1 | E104: -0.13870968 | F104: =E104-$E$121 -> 0.35053763 | M104: 0.33 | N104: 0.33 | P104: 0.33 | X104: =$F104*G104 -> 0 | Y104: =$F104*H104 -> 0 | Z104: =$F104*I104 -> 0 | AA104: =$F104*J104 -> 0 | AB104: =$F104*K104 -> 0 | AC104: =$F104*L104 -> 0 | AD104: =$F104*M104 -> 0.11567742 | AE104: =$F104*N104 -> 0.11567742 | ... AN104: =$F104*W104 -> 0
A105: I | B105: 25 | C105: 2 | D105: I_25_2 | E105: -0.13870968 | F105: =E105-$E$121 -> 0.35053763 | M105: 0.33 | N105: 0.33 | P105: 0.33 | X105: =$F105*G105 -> 0 | Y105: =$F105*H105 -> 0 | Z105: =$F105*I105 -> 0 | AA105: =$F105*J105 -> 0 | AB105: =$F105*K105 -> 0 | AC105: =$F105*L105 -> 0 | AD105: =$F105*M105 -> 0.11567742 | AE105: =$F105*N105 -> 0.11567742 | ... AN105: =$F105*W105 -> 0
A106: I | B106: 25 | C106: 5 | D106: I_25_5 | E106: -0.14516129 | F106: =E106-$E$121 -> 0.34408602 | M106: 0.33 | N106: 0.33 | P106: 0.33 | X106: =$F106*G106 -> 0 | Y106: =$F106*H106 -> 0 | Z106: =$F106*I106 -> 0 | AA106: =$F106*J106 -> 0 | AB106: =$F106*K106 -> 0 | AC106: =$F106*L106 -> 0 | AD106: =$F106*M106 -> 0.11354839 | AE106: =$F106*N106 -> 0.11354839 | ... AN106: =$F106*W106 -> 0
A107: I | B107: 26 | C107: 3 | D107: I_26_3 | E107: 0.34086022 | F107: =E107-$E$121 -> 0.83010753 | M107: 0.33 | N107: 0.33 | P107: 0.33 | X107: =$F107*G107 -> 0 | Y107: =$F107*H107 -> 0 | Z107: =$F107*I107 -> 0 | AA107: =$F107*J107 -> 0 | AB107: =$F107*K107 -> 0 | AC107: =$F107*L107 -> 0 | AD107: =$F107*M107 -> 0.27393548 | AE107: =$F107*N107 -> 0.27393548 | ... AN107: =$F107*W107 -> 0
A108: I | B108: 26 | C108: 5 | D108: I_26_5 | E108: 0.29784946 | F108: =E108-$E$121 -> 0.78709677 | M108: 0.33 | N108: 0.33 | P108: 0.33 | X108: =$F108*G108 -> 0 | Y108: =$F108*H108 -> 0 | Z108: =$F108*I108 -> 0 | AA108: =$F108*J108 -> 0 | AB108: =$F108*K108 -> 0 | AC108: =$F108*L108 -> 0 | AD108: =$F108*M108 -> 0.25974194 | AE108: =$F108*N108 -> 0.25974194 | ... AN108: =$F108*W108 -> 0
A109: I | B109: 26 | C109: 4 | D109: I_26_4 | E109: 0.26451613 | F109: =E109-$E$121 -> 0.75376344 | M109: 0.33 | N109: 0.33 | P109: 0.33 | X109: =$F109*G109 -> 0 | Y109: =$F109*H109 -> 0 | Z109: =$F109*I109 -> 0 | AA109: =$F109*J109 -> 0 | AB109: =$F109*K109 -> 0 | AC109: =$F109*L109 -> 0 | AD109: =$F109*M109 -> 0.24874194 | AE109: =$F109*N109 -> 0.24874194 | ... AN109: =$F109*W109 -> 0
A110: I | B110: 26 | C110: 2 | D110: I_26_2 | E110: 0.21935484 | F110: =E110-$E$121 -> 0.70860215 | M110: 0.33 | N110: 0.33 | P110: 0.33 | X110: =$F110*G110 -> 0 | Y110: =$F110*H110 -> 0 | Z110: =$F110*I110 -> 0 | AA110: =$F110*J110 -> 0 | AB110: =$F110*K110 -> 0 | AC110: =$F110*L110 -> 0 | AD110: =$F110*M110 -> 0.23383871 | AE110: =$F110*N110 -> 0.23383871 | ... AN110: =$F110*W110 -> 0
A111: I | B111: 26 | C111: 1 | D111: I_26_1 | E111: 0.20860215 | F111: =E111-$E$121 -> 0.69784946 | M111: 0.33 | N111: 0.33 | P111: 0.33 | X111: =$F111*G111 -> 0 | Y111: =$F111*H111 -> 0 | Z111: =$F111*I111 -> 0 | AA111: =$F111*J111 -> 0 | AB111: =$F111*K111 -> 0 | AC111: =$F111*L111 -> 0 | AD111: =$F111*M111 -> 0.23029032 | AE111: =$F111*N111 -> 0.23029032 | ... AN111: =$F111*W111 -> 0
A112: I | B112: 27 | C112: 4 | D112: I_27_4 | E112: 0.34086022 | F112: =E112-$E$121 -> 0.83010753 | M112: 0.33 | N112: 0.33 | P112: 0.33 | X112: =$F112*G112 -> 0 | Y112: =$F112*H112 -> 0 | Z112: =$F112*I112 -> 0 | AA112: =$F112*J112 -> 0 | AB112: =$F112*K112 -> 0 | AC112: =$F112*L112 -> 0 | AD112: =$F112*M112 -> 0.27393548 | AE112: =$F112*N112 -> 0.27393548 | ... AN112: =$F112*W112 -> 0
...

Sheet Tech. Support level EP2050+
D1: Alternative Name | E1: Biomass Boiler | F1: Heat Pump | G1: Methane Boiler | H1: CCGT (Ren. Methane) | I1: CHP (waste) | J1: CHP (Ren. Methane) | K1: Hydro (reservoir) | L1: Hydro (run of) | M1: PV (Roof) | N1: Pumped Hydro | O1: Wind | P1: CCGT (Nat Gas) with DACCS | Q1: Alpine PV | R1: Heavy EV | S1: Heavy FCEV | T1: Light EV | U1: Light FCEV
A2: I | B2: 1 | C2: 3 | D2: I_01_3 | E2: 0.11139785 | F2: 0.11139785 | G2: 0.11139785 | H2: 0 | I2: 0.11139785 | J2: 0.11139785 | K2: 0 | L2: 0 | M2: 0 | N2: 0 | O2: 0 | P2: 0 | Q2: 0 | R2: 0 | S2: 0 | T2: 0 | U2: 0
A3: I | B3: 3 | C3: 3 | D3: I_03_3 | E3: 0 | F3: 0 | G3: 0 | H3: 0 | I3: 0 | J3: 0.23548387 | K3: 0 | L3: 0 | M3: 0 | N3: 0 | O3: 0 | P3: 0 | Q3: 0 | R3: 0 | S3: 0 | T3: 0 | U3: 0
A4: I | B4: 4 | C4: 3 | D4: I_04_3 | E4: 0.082365591 | F4: 0.082365591 | G4: 0.082365591 | H4: 0 | I4: 0.082365591 | J4: 0.082365591 | K4: 0 | L4: 0 | M4: 0 | N4: 0 | O4: 0 | P4: 0 | Q4: 0 | R4: 0 | S4: 0 | T4: 0 | U4: 0
A5: I | B5: 5 | C5: 3 | D5: I_05_3 | E5: 0 | F5: 0 | G5: 0 | H5: 0 | I5: 0 | J5: 0 | K5: 0 | L5: 0 | M5: 0 | N5: 0 | O5: 0 | P5: 0 | Q5: 0 | R5: 0.10887097 | S5: 0.10887097 | T5: 0.10887097 | U5: 0.10887097
A6: I | B6: 6 | C6: 3 | D6: I_06_3 | E6: 0 | F6: 0 | G6: 0 | H6: 0.058817204 | I6: 0.058817204 | J6: 0.058817204 | K6: 0.058817204 | L6: 0.058817204 | M6: 0.058817204 | N6: 0.058817204 | O6: 0.058817204 | P6: 0.058817204 | Q6: 0.058817204 | R6: 0 | S6: 0 | T6: 0 | U6: 0
A7: I | B7: 9 | C7: 3 | D7: I_09_3 | E7: 0.17715054 | F7: 0.17715054 | G7: 0 | H7: 0 | I7: 0.17715054 | J7: 0.17715054 | K7: 0 | L7: 0 | M7: 0 | N7: 0 | O7: 0 | P7: 0 | Q7: 0 | R7: 0 | S7: 0 | T7: 0 | U7: 0
A8: I | B8: 10 | C8: 3 | D8: I_10_3 | E8: 0.14172043 | F8: 0.14172043 | G8: 0.14172043 | H8: 0 | I8: 0.14172043 | J8: 0.14172043 | K8: 0 | L8: 0 | M8: 0 | N8: 0 | O8: 0 | P8: 0 | Q8: 0 | R8: 0 | S8: 0 | T8: 0 | U8: 0
A9: I | B9: 11 | C9: 3 | D9: I_11_3 | E9: 0 | F9: 0.83010753 | G9: 0 | H9: 0 | I9: 0 | J9: 0 | K9: 0 | L9: 0 | M9: 0 | N9: 0 | O9: 0 | P9: 0 | Q9: 0 | R9: 0 | S9: 0 | T9: 0 | U9: 0
A10: I | B10: 12 | C10: 3 | D10: I_12_3 | E10: 0.53763441 | F10: 0 | G10: 0 | H10: 0 | I10: 0 | J10: 0 | K10: 0 | L10: 0 | M10: 0 | N10: 0 | O10: 0 | P10: 0 | Q10: 0 | R10: 0 | S10: 0 | T10: 0 | U10: 0
A11: I | B11: 13 | C11: 3 | D11: I_13_3 | E11: 0.056129032 | F11: 0.056129032 | G11: 0.056129032 | H11: 0 | I11: 0.056129032 | J11: 0.056129032 | K11: 0 | L11: 0 | M11: 0 | N11: 0 | O11: 0 | P11: 0 | Q11: 0 | R11: 0 | S11: 0 | T11: 0 | U11: 0
A12: I | B12: 14 | C12: 3 | D12: I_14_3 | E12: 0 | F12: 0 | G12: 0 | H12: 0.037741935 | I12: 0.037741935 | J12: 0.037741935 | K12: 0.037741935 | L12: 0.037741935 | M12: 0.037741935 | N12: 0.037741935 | O12: 0.037741935 | P12: 0.037741935 | Q12: 0.037741935 | R12: 0 | S12: 0 | T12: 0 | U12: 0
A13: I | B13: 15 | C13: 3 | D13: I_15_3 | E13: 0 | F13: 0 | G13: 0 | H13: 0 | I13: 0.2688172 | J13: 0.2688172 | K13: 0 | L13: 0 | M13: 0 | N13: 0 | O13: 0 | P13: 0 | Q13: 0 | R13: 0 | S13: 0 | T13: 0 | U13: 0
... A36: I | B36: 43 | C36: 3 | D36: I_43_3 | E36: 0 | F36: 0 | G36: 0 | H36: 0 | I36: 0 | J36: 0 | K36: 0 | L36: 0 | M36: 0 | N36: 0 | O36: 0 | P36: 0 | Q36: 0 | R36: 0 | S36: 0 | T36: 0.83010753 | U36: 0
A37: Tech. Support level EP2050+ | E37: =SUM(E2:E36) -> 1.1063978 | F37: =SUM(F2:F36) -> 1.398871 | G37: =SUM(G2:G36) -> 0.45441935 | H37: =SUM(H2:H36) -> 0.57221505 | I37: =SUM(I2:I36) -> 1.1264624 | J37: =SUM(J2:J36) -> 1.6452796 | K37: =SUM(K2:K36) -> 0.72355914 | L37: =SUM(L2:L36) -> 0.72355914 | ... U37: =SUM(U2:U36) -> 0.80931183

Sheet Relative tech support level
B1: Biomass Boiler | C1: Heat Pump | D1: Methane Boiler | E1: CCGT (Ren. Methane) | F1: CHP (waste) | G1: CHP (Ren. Methane) | H1: Hydro (reservoir) | I1: Hydro (run of) | J1: PV (Roof) | K1: Pumped Hydro | L1: Wind | M1: CCGT (Nat Gas) | N1: Alpine PV | O1: Heavy EV | P1: Heavy FCEV | Q1: Light EV | R1: Light FCEV
A2: EP2050+ | B2: NA | C2: NA | D2: NA | E2: NA | F2: NA | G2: NA | H2: NA | I2: NA | J2: NA | K2: NA | L2: NA | M2: NA | N2: NA | O2: NA | P2: NA | Q2: NA | R2: NA
A3: MIX | B3: =('[1]Scenario background'!M22-'[1]Scenario background'!M$21)/SUM('[1]Scenario background'!$M$21:$Y$21) -> -0.21647112 | C3: =('[1]Scenario background'!N22-'[1]Scenario background'!N$21)/SUM('[1]Scenario background'!$M$21:$Y$21) -> 0.26159794 | D3: =('[1]Scenario background'!O22-'[1]Scenario background'!O$21)/SUM('[1]Scenario background'!$M$21:$Y$21) -> -0.015878077 | E3: =('[1]Scenario background'!P22-'[1]Scenario background'!P$21)/SUM('[1]Scenario background'!$M$21:$Y$21) -> 0 | F3: =('[1]Scenario background'!Q22-'[1]Scenario background'!Q$21)/SUM('[1]Scenario background'!$M$21:$Y$21) -> 9.2798979e-09 | G3: =('[1]Scenario background'!R22-'[1]Scenario background'!R$21)/SUM('[1]Scenario background'!$M$21:$Y$21) -> -0.016220786 | H3: =('[1]Scenario background'!S22-'[1]Scenario background'!S$21)/SUM('[1]Scenario background'!$M$21:$Y$21) -> 0.0087329425 | I3: =('[1]Scenario background'!T22-'[1]Scenario background'!T$21)/SUM('[1]Scenario background'!$M$21:$Y$21) -> 0 | ... N3: =('[1]Scenario background'!Y22-'[1]Scenario background'!Y$21)/SUM('[1]Scenario background'!$M$21:$Y$21) -> 0 | O3: =('[1]Scenario background'!Z22-'[1]Scenario background'!Z$21)/SUM('[1]Scenario background'!$Z$21:$AC$21) -> 0 | P3: =('[1]Scenario background'!AA22-'[1]Scenario background'!AA$21)/SUM('[1]Scenario background'!$Z$21:$AC$21) -> 0 | Q3: =('[1]Scenario background'!AB22-'[1]Scenario background'!AB$21)/SUM('[1]Scenario background'!$Z$21:$AC$21) -> 0 | R3: =('[1]Scenario background'!AC22-'[1]Scenario background'!AC$21)/SUM('[1]Scenario background'!$Z$21:$AC$21) -> 0
A4: REMIX | B4: =('[1]Scenario background'!M23-'[1]Scenario background'!M$21)/SUM('[1]Scenario background'!$M$21:$Y$21) -> -0.095797733 | C4: =('[1]Scenario background'!N23-'[1]Scenario background'!N$21)/SUM('[1]Scenario background'!$M$21:$Y$21) -> 0.11241017 | D4: =('[1]Scenario background'!O23-'[1]Scenario background'!O$21)/SUM('[1]Scenario background'!$M$21:$Y$21) -> -0.015878077 | E4: =('[1]Scenario background'!P23-'[1]Scenario background'!P$21)/SUM('[1]Scenario background'!$M$21:$Y$21) -> 0.028315905 | F4: =('[1]Scenario background'!Q23-'[1]Scenario background'!Q$21)/SUM('[1]Scenario background'!$M$21:$Y$21) -> 1.120139e-08 | G4: =('[1]Scenario background'!R23-'[1]Scenario background'!R$21)/SUM('[1]Scenario background'!$M$21:$Y$21) -> -0.016220693 | H4: =('[1]Scenario background'!S23-'[1]Scenario background'!S$21)/SUM('[1]Scenario background'!$M$21:$Y$21) -> 0 | I4: =('[1]Scenario background'!T23-'[1]Scenario background'!T$21)/SUM('[1]Scenario background'!$M$21:$Y$21) -> 0 | ... N4: =('[1]Scenario background'!Y23-'[1]Scenario background'!Y$21)/SUM('[1]Scenario background'!$M$21:$Y$21) -> 0.046708011 | O4: =('[1]Scenario background'!Z23-'[1]Scenario background'!Z$21)/SUM('[1]Scenario background'!$Z$21:$AC$21) -> 0 | P4: =('[1]Scenario background'!AA23-'[1]Scenario background'!AA$21)/SUM('[1]Scenario background'!$Z$21:$AC$21) -> 0 | Q4: =('[1]Scenario background'!AB23-'[1]Scenario background'!AB$21)/SUM('[1]Scenario background'!$Z$21:$AC$21) -> 0 | R4: =('[1]Scenario background'!AC23-'[1]Scenario background'!AC$21)/SUM('[1]Scenario background'!$Z$21:$AC$21) -> 0
A5: H2 | B5: =('[1]Scenario background'!M24-'[1]Scenario background'!M$21)/SUM('[1]Scenario background'!$M$21:$Y$21) -> 0.014091794 | C5: =('[1]Scenario background'!N24-'[1]Scenario background'!N$21)/SUM('[1]Scenario background'!$M$21:$Y$21) -> -0.097378925 | D5: =('[1]Scenario background'!O24-'[1]Scenario background'!O$21)/SUM('[1]Scenario background'!$M$21:$Y$21) -> 0.10736227 | E5: =('[1]Scenario background'!P24-'[1]Scenario background'!P$21)/SUM('[1]Scenario background'!$M$21:$Y$21) -> 0 | F5: =('[1]Scenario background'!Q24-'[1]Scenario background'!Q$21)/SUM('[1]Scenario background'!$M$21:$Y$21) -> -3.7788348e-08 | G5: =('[1]Scenario background'!R24-'[1]Scenario background'!R$21)/SUM('[1]Scenario background'!$M$21:$Y$21) -> 1.1181451e-07 | H5: =('[1]Scenario background'!S24-'[1]Scenario background'!S$21)/SUM('[1]Scenario background'!$M$21:$Y$21) -> 0.014621063 | I5: =('[1]Scenario background'!T24-'[1]Scenario background'!T$21)/SUM('[1]Scenario background'!$M$21:$Y$21) -> 0 | ... N5: =('[1]Scenario background'!Y24-'[1]Scenario background'!Y$21)/SUM('[1]Scenario background'!$M$21:$Y$21) -> 0 | O5: =('[1]Scenario background'!Z24-'[1]Scenario background'!Z$21)/SUM('[1]Scenario background'!$Z$21:$AC$21) -> -0.041030901 | P5: =('[1]Scenario background'!AA24-'[1]Scenario background'!AA$21)/SUM('[1]Scenario background'!$Z$21:$AC$21) -> 0.041030901 | Q5: =('[1]Scenario background'!AB24-'[1]Scenario background'!AB$21)/SUM('[1]Scenario background'!$Z$21:$AC$21) -> -0.071419413 | R5: =('[1]Scenario background'!AC24-'[1]Scenario background'!AC$21)/SUM('[1]Scenario background'!$Z$21:$AC$21) -> 0.071419413
C7: Unit: TWh | E7: Power and heating
C8: Unit: Bil. Km | E8: Transport
B11: Biomass Boiler | C11: Heat Pump | D11: Methane Boiler | E11: CCGT (Ren. Methane) | F11: CHP (waste) | G11: CHP (Ren. Methane) | H11: Hydro (reservoir) | I11: Hydro (run of) | J11: PV (Roof) | K11: Pumped Hydro | L11: Wind | M11: CCGT (Nat Gas) | N11: Alpine PV | O11: Heavy EV | P11: Heavy FCEV | Q11: Light EV | R11: Light FCEV
A12: EP2050+ | B12: ='Tech. Support level EP2050+'!E37 -> 1.1063978 | C12: ='Tech. Support level EP2050+'!F37 -> 1.398871 | D12: ='Tech. Support level EP2050+'!G37 -> 0.45441935 | E12: ='Tech. Support level EP2050+'!H37 -> 0.57221505 | F12: ='Tech. Support level EP2050+'!I37 -> 1.1264624 | G12: ='Tech. Support level EP2050+'!J37 -> 1.6452796 | H12: ='Tech. Support level EP2050+'!K37 -> 0.72355914 | I12: ='Tech. Support level EP2050+'!L37 -> 0.72355914 | ... R12: ='Tech. Support level EP2050+'!U37 -> 0.80931183
A13: MIX | B13: =B$12*(1+B3) -> 0.86689467 | C13: =C$12*(1+C3) -> 1.7648127 | D13: =D$12*(1+D3) -> 0.44720405 | E13: =E$12*(1+E3) -> 0.57221505 | F13: =F$12*(1+F3) -> 1.1264624 | G13: =G$12*(1+G3) -> 1.6185918 | H13: =H$12*(1+H3) -> 0.72987794 | I13: =I$12*(1+I3) -> 0.72355914 | ... R13: =R$12*(1+R3) -> 0.80931183
A14: REMIX | B14: =B$12*(1+B4) -> 1.0004074 | C14: =C$12*(1+C4) -> 1.5561183 | D14: =D$12*(1+D4) -> 0.44720405 | E14: =E$12*(1+E4) -> 0.58841784 | F14: =F$12*(1+F4) -> 1.1264624 | G14: =G$12*(1+G4) -> 1.618592 | H14: =H$12*(1+H4) -> 0.72355914 | I14: =I$12*(1+I4) -> 0.72355914 | ... R14: =R$12*(1+R4) -> 0.80931183
A15: H2 | B15: =B$12*(1+B5) -> 1.121989 | C15: =C$12*(1+C5) -> 1.2626504 | D15: =D$12*(1+D5) -> 0.50320685 | E15: =E$12*(1+E5) -> 0.57221505 | F15: =F$12*(1+F5) -> 1.1264623 | G15: =G$12*(1+G5) -> 1.6452798 | H15: =H$12*(1+H5) -> 0.73413834 | I15: =I$12*(1+I5) -> 0.72355914 | ... R15: =R$12*(1+R5) -> 0.8671124

Sheet 2040-2050
A1: Policy ID | B1: Cost | C1: Effectiveness | D1: Acceptance of the tech. | E1: Acceptance of the policy instrument | F1: Administrative burden
A2: I_01_1 | B2: 5 | C2: 2 | D2: 4 | E2: 4 | F2: 4
A3: I_01_2 | B3: 5 | C3: 3 | D3: 4 | E3: 3 | F3: 4
A4: I_01_3 | B4: 5 | C4: 4 | D4: 4 | E4: 2 | F4: 4
A5: I_01_4 | B5: 5 | C5: 5 | D5: 4 | E5: 1 | F5: 4
A6: I_01_5 | B6: 5 | C6: 5 | D6: 4 | E6: 1 | F6: 4
A7: N_02_4 | B7: 5 | C7: 2 | D7: 4 | E7: 2 | F7: 3
A8: N_02_5 | B8: 5 | C8: 3 | D8: 4 | E8: 1 | F8: 3
A9: I_03_1 | B9: 4 | C9: 2 | D9: 4 | E9: 4 | F9: 3
A10: I_03_2 | B10: 3 | C10: 3 | D10: 4 | E10: 4 | F10: 3
A11: I_03_3 | B11: 2 | C11: 4 | D11: 4 | E11: 4 | F11: 3
A12: I_04_3 | B12: 5 | C12: 1 | D12: 4 | E12: 4 | F12: 4
A13: I_04_4 | B13: 5 | C13: 3 | D13: 4 | E13: 3 | F13: 4
... A188: N_46_5 | B188: 2 | C188: 4 | D188: 4 | E188: 4 | F188: 3
